Verilog/P3/Q2/decoder_2to4.v
module decoder_2to4(input [1:0] A, input E, output [3:0] O);
    buf B1(O[0], E&(!A[1])&(!A[0]));
    buf B2(O[1], E&(!A[1])&(A[0]));
    buf B3(O[2], E&(A[1])&(!A[0]));
    buf B4(O[3], E&(A[1])&(A[0]));
endmodule

//or simply do `include "Q1/decoder_2to4.v" and then instantiate the module

Verilog/P3/Q2/encoder_4to2.v
module encoder_4to2(input [3:0] A, input E, output [1:0] O);
    buf b1(O[1], E&(A[3]|A[2]));
    buf b2(O[0], E&(A[3]|A[1]));
endmodule

/*
Encoder takes 2^n inputs and gives n outputs. Converts a one hot input to binary output.
A3 A2 A1 A0 O1 O0
0  0  0  1  0  0
0  0  1  0  0  1 
0  1  0  0  1  0 
1  0  0  0  1  1
By noticing the pattern we can say - O1 = A3+A2 and O0 = A3+A1.
Extended truth table 
A3  A2  A1  A0  O1  O0
0   0   0   0   X   X (dont care when no input is given)
0   0   0   1   0   0
0   0   1   0   0   1
0   0   1   1   X   X
0   1   0   0   1   0
0   1   0   1   X   X
0   1   1   0   X   X
0   1   1   1   X   X
1   0   0   0   1   1
1   0   0   1   X   X
1   0   1   0   X   X
1   0   1   1   X   X
1   1   0   0   X   X
1   1   0   1   X   X
1   1   1   0   X   X
1   1   1   1   X   X
Using K maps to solve for O1 and O0 we get 
O1 = 
O0 = 
*/

Verilog/P3/Q2/rollcall_match.v
// include decoder and encoder here, if you plan to use them
// see tb_rollcall.v for expected behavior
`include "decoder_2to4.v"
`include "encoder_4to2.v"
module rollcall(
    input [1:0] S0, input [1:0] S1, input [1:0] S2, input [1:0] S3, 
    input [1:0] PAT,
    input MODE, 
    output [3:0] MATCH,
    output ANY,
    output PAR,
    output [1:0] FIRST,
    output [1:0] Y
);
    wire [3:0] P1, P2, P3, P4, Con; //storing pairs 
    //buf B1(P1, {S0, S1}); does not work, buf is primitive and expects single bit inputs/outputs
    buf B1_0(P1[3], S0[1]); 
    buf B1_1(P1[2], S0[0]);
    buf B1_2(P1[1], S1[1]);
    buf B1_3(P1[0], S1[0]); 
    buf B2_0(P2[3], S1[1]);
    buf B2_1(P2[2], S1[0]);
    buf B2_2(P2[1], S2[1]);
    buf B2_3(P2[0], S2[0]);
    buf B3_0(P3[3], S2[1]);
    buf B3_1(P3[2], S2[0]);
    buf B3_2(P3[1], S3[1]);
    buf B3_3(P3[0], S3[0]);
    buf B4_0(P4[3], S3[1]);
    buf B4_1(P4[2], S3[0]);
    buf B4_2(P4[1], S0[1]);
    buf B4_3(P4[0], S0[0]);
    buf B5_0(Con[3], PAT[1]);
    buf B5_1(Con[2], PAT[0]);
    buf B5_2(Con[1], (!PAT[1]&!PAT[0]&MODE)|(!PAT[1]&PAT[0]&!MODE)|(PAT[1]&!PAT[0]&!MODE)|(PAT[1]&PAT[0]&MODE));
    buf B5_3(Con[0], !PAT[0]);      
    //buf B5(Con, {PAT, (!PAT[1]&!PAT[0]&MODE)|(!PAT[1]&PAT[0]&!MODE)|(PAT[1]&!PAT[0]&!MODE)|(PAT[1]&PAT[0]&MODE), !PAT[0]}); wont work for the same reason as earlier
    isequal IE1(P1, Con, MATCH[0]);
    isequal IE2(P2, Con, MATCH[1]);
    isequal IE3(P3, Con, MATCH[2]);
    isequal IE4(P4, Con, MATCH[3]);

    buf B6(ANY, (MATCH[0] | MATCH[1] | MATCH[2] | MATCH[3]));
    buf B7(PAR, (MATCH[0] ^ MATCH[1] ^ MATCH[2] ^ MATCH[3])); //in this specific case, simply do buf B7(PAR, ANY);

    encoder_4to2 ENC1(MATCH, ANY, FIRST);

    buf B8(Y[1], ANY&Con[1]);
    buf B9(Y[0], ANY&Con[0]);    
    /*
    wire [3:0] dS0, dS1, dS2, dS3, dPAT;
    decoder_2to4 DEC0(S0, 1'b1, dS0);
    decoder_2to4 DEC1(S1, 1'b1, dS1);
    decoder_2to4 DEC2(S2, 1'b1, dS2);
    decoder_2to4 DEC3(S3, 1'b1, dS3);
    decoder_2to4 DECP(PAT, 1'b1, dPAT);
    */
endmodule


//creating module for equality check
module isequal(input[3:0] A, input [3:0] B, output O);
    buf BE(O, ((A[3] ~^ B[3]) & (A[2] ~^ B[2]) & (A[1] ~^ B[1]) & (A[0] ~^ B[0])));
endmodule

Verilog/P3/Q2/tb_rollcall.v
`include "rollcall_match.v"

module tb_rollcall_match;

reg [1:0] S0, S1, S2, S3;
reg [1:0] PAT;
reg MODE;

wire [3:0] MATCH;
wire ANY;
wire PAR;
wire [1:0] FIRST;
wire [1:0] Y;

rollcall r(S0, S1, S2, S3, PAT, MODE, MATCH, ANY, PAR, FIRST, Y);

initial begin
    $dumpfile("tb_rollcall_match.vcd");
    $dumpvars(0, tb_rollcall_match);

    S0 = 2; S1 = 3; S2 = 1; S3 = 0; PAT = 2; MODE = 0;
    // Target = (2,3). Pairs: (2,3), (3,1), (1,0), (0,2). Match at index 0.
    // MATCH=0001, ANY=1, PAR=1, FIRST=00, Y=3

    #10 S0 = 1; S1 = 0; S2 = 3; S3 = 2; PAT = 2; MODE = 1;
    // Target = (2,1). Pairs: (1,0), (0,3), (3,2), (2,1). Match at index 3.
    // MATCH=1000, ANY=1, PAR=1, FIRST=11, Y=1

    #10 S0 = 0; S1 = 1; S2 = 2; S3 = 3; PAT = 0; MODE = 0;
    // Target = (0,1). Pairs: (0,1), (1,2), (2,3), (3,0). Match at index 0.
    // MATCH=0001, ANY=1, PAR=1, FIRST=00, Y=1

    #10 S0 = 3; S1 = 2; S2 = 1; S3 = 0; PAT = 0; MODE = 1;
    // Target = (0,3). Pairs: (3,2), (2,1), (1,0), (0,3). Match at index 3.
    // MATCH=1000, ANY=1, PAR=1, FIRST=11, Y=3

    #10 S0 = 1; S1 = 2; S2 = 3; S3 = 0; PAT = 1; MODE = 0;
    // Target = (1,2). Pairs: (1,2), (2,3), (3,0), (0,1). Match at index 0.
    // MATCH=0001, ANY=1, PAR=1, FIRST=00, Y=2

    #10 S0 = 0; S1 = 3; S2 = 2; S3 = 1; PAT = 3; MODE = 1;
    // Target = (3,2). Pairs: (0,3), (3,2), (2,1), (1,0). Match at index 1.
    // MATCH=0010, ANY=1, PAR=1, FIRST=01, Y=2

    #10 S0 = 3; S1 = 3; S2 = 3; S3 = 3; PAT = 2; MODE = 0;
    // Target = (2,3). All pairs are (3,3). No match.
    // MATCH=0000, ANY=0, PAR=0, FIRST=00, Y=0

    #10 S0 = 0; S1 = 2; S2 = 1; S3 = 3; PAT = 1; MODE = 0;
    // Target = (1,2). Pairs: (0,2), (2,1), (1,3), (3,0). No exact (1,2). No match.
    // MATCH=0000, ANY=0, PAR=0, FIRST=00, Y=0

    #10 S0 = 0; S1 = 3; S2 = 2; S3 = 1; PAT = 2; MODE = 1;
    // Target = (2,1). Pairs: (0,3), (3,2), (2,1), (1,0). Match at index 2.
    // MATCH=0100, ANY=1, PAR=1, FIRST=10, Y=1

    #10 S0 = 0; S1 = 3; S2 = 1; S3 = 2; PAT = 3; MODE = 1;
    // Target = (3,2). Pairs: (0,3), (3,1), (1,2), (2,0). No (3,2). No match.
    // MATCH=0000, ANY=0, PAR=0, FIRST=00, Y=0

    #10 S0 = 2; S1 = 1; S2 = 3; S3 = 0; PAT = 1; MODE = 1;
    // Target = (1,0). Pairs: (2,1), (1,3), (3,0), (0,2). No (1,0). No match.
    // MATCH=0000, ANY=0, PAR=0, FIRST=00, Y=0

    #10 S0 = 0; S1 = 2; S2 = 3; S3 = 1; PAT = 3; MODE = 0;
    // Target = (3,0). Pairs: (0,2), (2,3), (3,1), (1,0). No (3,0). No match.
    // MATCH=0000, ANY=0, PAR=0, FIRST=00, Y=0

    // You can add more test cases if you want
    #20 $finish;
end

initial begin
    // try to understand the difference between %0d and %d, similarly between %0b and %b
    $monitor("S0 S1 S2 S3 = %0d %0d %0d %0d, PAT = %0d, MODE = %0d, MATCH = %b, ANY = %0d, PAR = %0d, FIRST = %b, Y = %0d",
            S0, S1, S2, S3, PAT, MODE, MATCH, ANY, PAR, FIRST, Y);
end

endmodule

Verilog/P3/Q2/tb_rollcall_match.vcd
$date
	Mon Sep 15 16:58:21 2025
$end
$version
	Icarus Verilog
$end
$timescale
	1s
$end
$scope module tb_rollcall_match $end
$var wire 2 ! Y [1:0] $end
$var wire 1 " PAR $end
$var wire 4 # MATCH [3:0] $end
$var wire 2 $ FIRST [1:0] $end
$var wire 1 % ANY $end
$var reg 1 & MODE $end
$var reg 2 ' PAT [1:0] $end
$var reg 2 ( S0 [1:0] $end
$var reg 2 ) S1 [1:0] $end
$var reg 2 * S2 [1:0] $end
$var reg 2 + S3 [1:0] $end
$scope module r $end
$var wire 1 % ANY $end
$var wire 1 & MODE $end
$var wire 1 " PAR $end
$var wire 2 , PAT [1:0] $end
$var wire 2 - S0 [1:0] $end
$var wire 2 . S1 [1:0] $end
$var wire 2 / S2 [1:0] $end
$var wire 2 0 S3 [1:0] $end
$var wire 2 1 Y [1:0] $end
$var wire 4 2 P4 [3:0] $end
$var wire 4 3 P3 [3:0] $end
$var wire 4 4 P2 [3:0] $end
$var wire 4 5 P1 [3:0] $end
$var wire 4 6 MATCH [3:0] $end
$var wire 2 7 FIRST [1:0] $end
$var wire 4 8 Con [3:0] $end
$scope module ENC1 $end
$var wire 4 9 A [3:0] $end
$var wire 1 % E $end
$var wire 2 : O [1:0] $end
$upscope $end
$scope module IE1 $end
$var wire 4 ; A [3:0] $end
$var wire 4 < B [3:0] $end
$var wire 1 = O $end
$upscope $end
$scope module IE2 $end
$var wire 4 > A [3:0] $end
$var wire 4 ? B [3:0] $end
$var wire 1 @ O $end
$upscope $end
$scope module IE3 $end
$var wire 4 A A [3:0] $end
$var wire 4 B B [3:0] $end
$var wire 1 C O $end
$upscope $end
$scope module IE4 $end
$var wire 4 D A [3:0] $end
$var wire 4 E B [3:0] $end
$var wire 1 F O $end
$upscope $end
$upscope $end
$upscope $end
$enddefinitions $end
$comment Show the parameter values. $end
$dumpall
$end
#0
$dumpvars
0F
b1011 E
b10 D
0C
b1011 B
b100 A
0@
b1011 ?
b1101 >
1=
b1011 <
b1011 ;
b0 :
b1 9
b1011 8
b0 7
b1 6
b1011 5
b1101 4
b100 3
b10 2
b11 1
b0 0
b1 /
b11 .
b10 -
b10 ,
b0 +
b1 *
b11 )
b10 (
b10 '
0&
1%
b0 $
b1 #
1"
b11 !
$end
#10
b11 $
b11 7
b11 :
1%
1"
1F
b1 !
b1 1
b1000 #
b1000 6
b1000 9
0=
b1001 8
b1001 <
b1001 ?
b1001 B
b1001 E
b1110 3
b1110 A
b11 4
b11 >
b100 5
b100 ;
b1001 2
b1001 D
1&
b10 +
b10 0
b11 *
b11 /
b0 )
b0 .
b1 (
b1 -
#20
b0 $
b0 7
b0 :
1%
1"
1=
b1 !
b1 1
b1 #
b1 6
b1 9
0F
b1 8
b1 <
b1 ?
b1 B
b1 E
b1011 3
b1011 A
b110 4
b110 >
b1 5
b1 ;
b1100 2
b1100 D
0&
b0 '
b0 ,
b11 +
b11 0
b10 *
b10 /
b1 )
b1 .
b0 (
b0 -
#30
b11 $
b11 7
b11 :
1%
1"
1F
b11 !
b11 1
b1000 #
b1000 6
b1000 9
0=
b11 8
b11 <
b11 ?
b11 B
b11 E
b100 3
b100 A
b1001 4
b1001 >
b1110 5
b1110 ;
b11 2
b11 D
1&
b0 +
b0 0
b1 *
b1 /
b10 )
b10 .
b11 (
b11 -
#40
b0 $
b0 7
b0 :
1%
1"
1=
b1 #
b1 6
b1 9
0F
b10 !
b10 1
b110 8
b110 <
b110 ?
b110 B
b110 E
b1011 4
b1011 >
b1100 3
b1100 A
b110 5
b110 ;
b1 2
b1 D
0&
b1 '
b1 ,
b11 *
b11 /
b1 (
b1 -
#50
b10 !
b10 1
b1 $
b1 7
b1 :
1%
1"
1@
b10 #
b10 6
b10 9
0=
b1110 8
b1110 <
b1110 ?
b1110 B
b1110 E
b1001 3
b1001 A
b1110 4
b1110 >
b11 5
b11 ;
b100 2
b100 D
1&
b11 '
b11 ,
b1 +
b1 0
b10 *
b10 /
b11 )
b11 .
b0 (
b0 -
#60
0%
0"
b0 $
b0 7
b0 :
b0 #
b0 6
b0 9
0@
b0 !
b0 1
b1011 8
b1011 <
b1011 ?
b1011 B
b1011 E
b1111 4
b1111 >
b1111 3
b1111 A
b1111 5
b1111 ;
b1111 2
b1111 D
0&
b10 '
b10 ,
b11 +
b11 0
b11 *
b11 /
b11 (
b11 -
#70
b110 8
b110 <
b110 ?
b110 B
b110 E
b111 3
b111 A
b1001 4
b1001 >
b10 5
b10 ;
b1100 2
b1100 D
b1 '
b1 ,
b1 *
b1 /
b10 )
b10 .
b0 (
b0 -
#80
b1 !
b1 1
b10 $
b10 7
b10 :
1%
1"
b100 #
b100 6
b100 9
1C
b1001 8
b1001 <
b1001 ?
b1001 B
b1001 E
b100 2
b100 D
b1001 3
b1001 A
b11 5
b11 ;
b1110 4
b1110 >
1&
b10 '
b10 ,
b1 +
b1 0
b10 *
b10 /
b11 )
b11 .
#90
0%
0"
b0 $
b0 7
b0 :
b0 #
b0 6
b0 9
0C
b0 !
b0 1
b1110 8
b1110 <
b1110 ?
b1110 B
b1110 E
b1000 2
b1000 D
b1101 4
b1101 >
b110 3
b110 A
b11 '
b11 ,
b10 +
b10 0
b1 *
b1 /
#100
b100 8
b100 <
b100 ?
b100 B
b100 E
b1100 3
b1100 A
b111 4
b111 >
b1001 5
b1001 ;
b10 2
b10 D
b1 '
b1 ,
b0 +
b0 0
b11 *
b11 /
b1 )
b1 .
b10 (
b10 -
#110
b1100 8
b1100 <
b1100 ?
b1100 B
b1100 E
b1101 3
b1101 A
b1011 4
b1011 >
b10 5
b10 ;
b100 2
b100 D
0&
b11 '
b11 ,
b1 +
b1 0
b10 )
b10 .
b0 (
b0 -
