Verilog/P3/Q3/mux_2to1.v
module mux_2to1(input [1:0] A, input S, output O);
    buf B1(O, ((!S)&A[0])|(S&A[1])); //outputs A[1] if S is 1 and A[0] if S is 0
endmodule

Verilog/P3/Q3/P1/mux_design.v
// include 2:1 mux here with the correct file path
`include "../mux_2to1.v"
module mux_design(input A, input B, input C, output Z1);
    //WRITE YOUR CODE HERE
    /*
    wire [1:0] In;
    buf B1(In[1], B^C); //or implement this also via mux
    buf B2(In[0], B&C);
    mux_2to1 M211(In, A, Z1);
    */
    wire w1, w2;
    mux_2to1 M211({C, 1'b0}, B, w1);
    mux_2to1 M212({~C, C}, B, w2);
    mux_2to1 M213({w2, w1}, A, Z1);
endmodule

/*
Z1 = ABC' + AB'C + A'BC
A B C | Z1 
0 0 0 |  0 
0 0 1 |  0 
0 1 0 |  0 
0 1 1 |  1 
1 0 0 |  0 
1 0 1 |  1 
1 1 0 |  1     
1 1 1 |  0 

We need to use three 2:1 muxes, hints at usage of multiple select lines
So look at pattern when A and B are my select lines
*/

Verilog/P3/Q3/P1/testbench.v
`include "mux_design.v"

module tb_mux_design;

reg A, B, C;
wire Z1;

mux_design md(A, B, C, Z1);

initial begin
    $dumpfile("tb_mux_design.vcd");
    $dumpvars(0, tb_mux_design);

    A = 1'b0; B = 1'b0; C = 1'b0;
    #10 A = 1'b0; B = 1'b0; C = 1'b1;
    #10 A = 1'b0; B = 1'b1; C = 1'b0;
    #10 A = 1'b0; B = 1'b1; C = 1'b1;
    #10 A = 1'b1; B = 1'b0; C = 1'b0;
    #10 A = 1'b1; B = 1'b0; C = 1'b1;
    #10 A = 1'b1; B = 1'b1; C = 1'b0;
    #10 A = 1'b1; B = 1'b1; C = 1'b1;
    #10 $finish;
end

initial begin
    $monitor("time = %0d, A = %b, B = %b, C = %b, Z1 = %b", $time, A, B, C, Z1);
end

endmodule

Verilog/P3/Q3/P1/tb_mux_design.vcd
$date
	Tue Sep 16 15:49:48 2025
$end
$version
	Icarus Verilog
$end
$timescale
	1s
$end
$scope module tb_mux_design $end
$var wire 1 ! Z1 $end
$var reg 1 " A $end
$var reg 1 # B $end
$var reg 1 $ C $end
$scope module md $end
$var wire 1 " A $end
$var wire 1 # B $end
$var wire 1 $ C $end
$var wire 1 % w2 $end
$var wire 1 & w1 $end
$var wire 1 ! Z1 $end
$scope module M211 $end
$var wire 2 ' A [1:0] $end
$var wire 1 & O $end
$var wire 1 # S $end
$upscope $end
$scope module M212 $end
$var wire 2 ( A [1:0] $end
$var wire 1 % O $end
$var wire 1 # S $end
$upscope $end
$scope module M213 $end
$var wire 2 ) A [1:0] $end
$var wire 1 ! O $end
$var wire 1 " S $end
$upscope $end
$upscope $end
$upscope $end
$enddefinitions $end
$comment Show the parameter values. $end
$dumpall
$end
#0
$dumpvars
b0 )
b10 (
b0 '
0&
0%
0$
0#
0"
0!
$end
#10
b10 )
1%
b10 '
b1 (
1$
#20
0!
0&
b10 )
1%
b0 '
b10 (
0$
1#
#30
1!
0%
b1 )
1&
b10 '
b1 (
1$
#40
0&
b0 )
0%
0!
b0 '
b10 (
0$
0#
1"
#50
1!
b10 )
1%
b10 '
b1 (
1$
#60
1!
0&
b10 )
1%
b0 '
b10 (
0$
1#
#70
0!
0%
b1 )
1&
b10 '
b1 (
1$
