Verilog/L4/src/mux_2to1.v
module mux_2to1(
    output y,
    input in0, in1, sel
);
    wire nsel, w1, w2;
    not n1(nsel,sel);
    and a1(w1, nsel, in0);
    and a2(w2, sel, in1);
    or o1(y, w1, w2);  
endmodule

Verilog/L4/tb/tb_mux_2to1.v
`include "src/mux_2to1.v"

module tb_mux_2to1;

    // Inputs
    reg in0, in1, sel;

    // Output
    wire y;

    // Instantiate the mux
    mux_2to1 uut (
        .y(y),
        .in0(in0),
        .in1(in1),
        .sel(sel)
    );

    initial begin
        $dumpfile("public/vcd/wave_mux_2to1.vcd");
        $dumpvars(0, tb_mux_2to1);

        $display("\nTesting 2-to-1 Multiplexer\n");
        $display("|%-5s|%-5s|%-5s|%-5s|%-5s|", "Time", "in0", "in1", "sel", "y");
        $display("|-----|-----|-----|-----|-----|");

        $monitor("|%-5d|%-5b|%-5b|%-5b|%-5b|", $time, in0, in1, sel, y);

        // Apply test cases
            in0 = 0; in1 = 0; sel = 0;
        #10 in0 = 0; in1 = 0; sel = 1;
        #10 in0 = 0; in1 = 1; sel = 0;
        #10 in0 = 0; in1 = 1; sel = 1;
        #10 in0 = 1; in1 = 0; sel = 0;
        #10 in0 = 1; in1 = 0; sel = 1;
        #10 in0 = 1; in1 = 1; sel = 0;
        #10 in0 = 1; in1 = 1; sel = 1;

        #10 $finish;
    end

endmodule

Verilog/L4/public/vcd/wave_mux_2to1.vcd
$date
	Wed Sep 10 15:44:10 2025
$end
$version
	Icarus Verilog
$end
$timescale
	1s
$end
$scope module tb_mux_2to1 $end
$var wire 1 ! y $end
$var reg 1 " in0 $end
$var reg 1 # in1 $end
$var reg 1 $ sel $end
$scope module uut $end
$var wire 1 " in0 $end
$var wire 1 # in1 $end
$var wire 1 % nsel $end
$var wire 1 $ sel $end
$var wire 1 & w1 $end
$var wire 1 ' w2 $end
$var wire 1 ! y $end
$upscope $end
$upscope $end
$enddefinitions $end
#0
$dumpvars
0'
0&
1%
0$
0#
0"
0!
$end
#10
0%
1$
#20
1%
0$
1#
#30
1!
0%
1'
1$
#40
1&
1!
1%
0'
0$
0#
1"
#50
0!
0&
0%
1$
#60
1!
1&
1%
0$
1#
#70
0&
0%
1'
1$
