Verilog/L4/src/half_adder.v
module half_adder(
    output sum, carry,
    input a, b
);
    xor x1(sum, a, b);
    and a1(carry, a, b);

endmodule

Verilog/L4/src/full_adder.v
// include your half adder module
// prefix the included module name with "src/"
`include "src/half_adder.v"
module full_adder(
    output sum, carry_out,
    input a, b, carry_in
);
    wire s1, c1, c2;
    half_adder h1(s1, c1, a, b);
    half_adder h2(sum, c2, s1, carry_in);
    or o1(carry_out, c1, c2);

endmodule

Verilog/L4/tb/tb_full_adder.v
`include "src/full_adder.v"

module tb_full_adder;

    // Inputs
    reg a, b, cin;

    // Outputs
    wire sum, cout;

    // Instantiate the full adder
    full_adder uut (
        .a(a),
        .b(b),
        .carry_in(cin),
        .sum(sum),
        .carry_out(cout)
    );

    initial begin
        $dumpfile("public/vcd/wave_full_adder.vcd");
        $dumpvars(0, tb_full_adder);

        $display("\nTesting 1-bit Full Adder\n");
        $display("|%-5s|%-5s|%-5s|%-5s|%-5s|%-5s|", "Time", "a", "b", "cin", "sum", "cout");
        $display("|-----|-----|-----|-----|-----|-----|");
        $monitor("|%-5d|%-5b|%-5b|%-5b|%-5b|%-5b|", $time, a, b, cin, sum, cout);

        // Apply test cases
            a = 0; b = 0; cin = 0;
        #10 a = 0; b = 0; cin = 1;
        #10 a = 0; b = 1; cin = 0;
        #10 a = 0; b = 1; cin = 1;
        #10 a = 1; b = 0; cin = 0;
        #10 a = 1; b = 0; cin = 1;
        #10 a = 1; b = 1; cin = 0;
        #10 a = 1; b = 1; cin = 1;

        #10 $finish;
    end

endmodule

Verilog/L4/public/vcd/wave_full_adder.vcd
$date
	Wed Sep 10 15:44:09 2025
$end
$version
	Icarus Verilog
$end
$timescale
	1s
$end
$scope module tb_full_adder $end
$var wire 1 ! sum $end
$var wire 1 " cout $end
$var reg 1 # a $end
$var reg 1 $ b $end
$var reg 1 % cin $end
$scope module uut $end
$var wire 1 # a $end
$var wire 1 $ b $end
$var wire 1 % carry_in $end
$var wire 1 " carry_out $end
$var wire 1 ! sum $end
$var wire 1 & s1 $end
$var wire 1 ' c2 $end
$var wire 1 ( c1 $end
$scope module h1 $end
$var wire 1 # a $end
$var wire 1 $ b $end
$var wire 1 ( carry $end
$var wire 1 & sum $end
$upscope $end
$scope module h2 $end
$var wire 1 & a $end
$var wire 1 % b $end
$var wire 1 ' carry $end
$var wire 1 ! sum $end
$upscope $end
$upscope $end
$upscope $end
$enddefinitions $end
#0
$dumpvars
0(
0'
0&
0%
0$
0#
0"
0!
$end
#10
1!
1%
#20
1&
0%
1$
#30
1"
0!
1'
1%
#40
0"
1!
0'
0%
0$
1#
#50
1"
0!
1'
1%
#60
0'
0&
1(
0%
1$
#70
1!
1%
