Verilog/L4/src/mux_2to1.v
module mux_2to1(
    output y,
    input in0, in1, sel
);
    wire nsel, w1, w2;
    not n1(nsel,sel);
    and a1(w1, nsel, in0);
    and a2(w2, sel, in1);
    or o1(y, w1, w2);  
endmodule

Verilog/L4/src/higher_order_muxes.v
// include your 2:1 mux module
// prefix the included module name with "src/"
`include "src/mux_2to1.v"
module mux_6to3(
    output[2:0] y,
    input[2:0] in0, in1,
    input sel
);
    mux_2to1 m1(y[0], in0[0], in1[0], sel);
    mux_2to1 m2(y[1], in0[1], in1[1], sel);
    mux_2to1 m3(y[2], in0[2], in1[2], sel);

endmodule


module mux_8to4(
    output[3:0] y,
    input[3:0] in0, in1,
    input sel
);
    mux_2to1 m4(y[0], in0[0], in1[0], sel);
    mux_2to1 m5(y[1], in0[1], in1[1], sel);
    mux_2to1 m6(y[2], in0[2], in1[2], sel);
    mux_2to1 m7(y[3], in0[3], in1[3], sel);

endmodule

Verilog/L4/tb/tb_higher_order_muxes.v
`timescale 1ns/1ps
`include "src/higher_order_muxes.v"

module tb_muxes;

    // Signals for 6:3 MUX
    reg  [2:0] in0_3, in1_3;
    reg        sel_3;
    wire [2:0] out_3;

    // Signals for 8:4 MUX
    reg  [3:0] in0_4, in1_4;
    reg        sel_4;
    wire [3:0] out_4;

    // Instantiate 6:3 mux
    mux_6to3 uut6 (
        .in0(in0_3),
        .in1(in1_3),
        .sel(sel_3),
        .y(out_3)
    );

    // Instantiate 8:4 mux
    mux_8to4 uut8 (
        .in0(in0_4),
        .in1(in1_4),
        .sel(sel_4),
        .y(out_4)
    );

    initial begin
        $dumpfile("public/vcd/wave_higher_order_muxes.vcd");
        $dumpvars(0, tb_muxes);

        // --- Test 6:3 MUX ---
        $display("\nTesting 6:3 MUX\n");
        $display("|%-5s|%-5s|%-5s|%-5s|%-5s|",
                 "Time", "in0", "in1", "sel", "y");
        $display("|-----|-----|-----|-----|-----|");

        in0_3 = 3'b010; in1_3 = 3'b101; sel_3 = 1'b0; #10;
        $display("|%-5d|%-5b|%-5b|%-5b|%-5b|",
                 $time, in0_3, in1_3, sel_3, out_3);

        in0_3 = 3'b010; in1_3 = 3'b101; sel_3 = 1'b1; #10;
        $display("|%-5d|%-5b|%-5b|%-5b|%-5b|",
                 $time, in0_3, in1_3, sel_3, out_3);

        in0_3 = 3'b111; in1_3 = 3'b000; sel_3 = 1'b0; #10;
        $display("|%-5d|%-5b|%-5b|%-5b|%-5b|",
                 $time, in0_3, in1_3, sel_3, out_3);

        in0_3 = 3'b100; in1_3 = 3'b101; sel_3 = 1'b0; #10;
        $display("|%-5d|%-5b|%-5b|%-5b|%-5b|",
                 $time, in0_3, in1_3, sel_3, out_3);

        in0_3 = 3'b001; in1_3 = 3'b110; sel_3 = 1'b1; #10;
        $display("|%-5d|%-5b|%-5b|%-5b|%-5b|",
                 $time, in0_3, in1_3, sel_3, out_3);

        in0_3 = 3'b010; in1_3 = 3'b011; sel_3 = 1'b1; #10;
        $display("|%-5d|%-5b|%-5b|%-5b|%-5b|",
                 $time, in0_3, in1_3, sel_3, out_3);

        // --- Test 8:4 MUX ---
        $display("\nTesting 8:4 MUX\n");
        $display("|%-5s|%-5s|%-5s|%-5s|%-5s|",
                 "Time", "in0", "in1", "sel", "y");
        $display("|-----|-----|-----|-----|-----|");

        in0_4 = 4'b1010; in1_4 = 4'b0111; sel_4 = 1'b0; #10;
        $display("|%-5d|%-5b|%-5b|%-5b|%-5b|",
                 $time, in0_4, in1_4, sel_4, out_4);

        in0_4 = 4'b0110; in1_4 = 4'b1001; sel_4 = 1'b1; #10;
        $display("|%-5d|%-5b|%-5b|%-5b|%-5b|",
                 $time, in0_4, in1_4, sel_4, out_4);

        in0_4 = 4'b0111; in1_4 = 4'b0100; sel_4 = 1'b0; #10;
        $display("|%-5d|%-5b|%-5b|%-5b|%-5b|",
                 $time, in0_4, in1_4, sel_4, out_4);

        in0_4 = 4'b1100; in1_4 = 4'b1101; sel_4 = 1'b0; #10;
        $display("|%-5d|%-5b|%-5b|%-5b|%-5b|",
                 $time, in0_4, in1_4, sel_4, out_4);

        in0_4 = 4'b0001; in1_4 = 4'b1110; sel_4 = 1'b1; #10;
        $display("|%-5d|%-5b|%-5b|%-5b|%-5b|",
                 $time, in0_4, in1_4, sel_4, out_4);

        in0_4 = 4'b0101; in1_4 = 4'b0011; sel_4 = 1'b1; #10;
        $display("|%-5d|%-5b|%-5b|%-5b|%-5b|",
                 $time, in0_4, in1_4, sel_4, out_4);

        #10 $finish;
    end

endmodule

Verilog/L4/public/vcd/wave_higher_order_muxes.vcd
$date
	Wed Sep 10 15:44:10 2025
$end
$version
	Icarus Verilog
$end
$timescale
	1ps
$end
$scope module tb_muxes $end
$var wire 4 ! out_4 [3:0] $end
$var wire 3 " out_3 [2:0] $end
$var reg 3 # in0_3 [2:0] $end
$var reg 4 $ in0_4 [3:0] $end
$var reg 3 % in1_3 [2:0] $end
$var reg 4 & in1_4 [3:0] $end
$var reg 1 ' sel_3 $end
$var reg 1 ( sel_4 $end
$scope module uut6 $end
$var wire 3 ) in0 [2:0] $end
$var wire 3 * in1 [2:0] $end
$var wire 1 ' sel $end
$var wire 3 + y [2:0] $end
$scope module m1 $end
$var wire 1 , in0 $end
$var wire 1 - in1 $end
$var wire 1 . nsel $end
$var wire 1 ' sel $end
$var wire 1 / w1 $end
$var wire 1 0 w2 $end
$var wire 1 1 y $end
$upscope $end
$scope module m2 $end
$var wire 1 2 in0 $end
$var wire 1 3 in1 $end
$var wire 1 4 nsel $end
$var wire 1 ' sel $end
$var wire 1 5 w1 $end
$var wire 1 6 w2 $end
$var wire 1 7 y $end
$upscope $end
$scope module m3 $end
$var wire 1 8 in0 $end
$var wire 1 9 in1 $end
$var wire 1 : nsel $end
$var wire 1 ' sel $end
$var wire 1 ; w1 $end
$var wire 1 < w2 $end
$var wire 1 = y $end
$upscope $end
$upscope $end
$scope module uut8 $end
$var wire 4 > in0 [3:0] $end
$var wire 4 ? in1 [3:0] $end
$var wire 1 ( sel $end
$var wire 4 @ y [3:0] $end
$scope module m4 $end
$var wire 1 A in0 $end
$var wire 1 B in1 $end
$var wire 1 C nsel $end
$var wire 1 ( sel $end
$var wire 1 D w1 $end
$var wire 1 E w2 $end
$var wire 1 F y $end
$upscope $end
$scope module m5 $end
$var wire 1 G in0 $end
$var wire 1 H in1 $end
$var wire 1 I nsel $end
$var wire 1 ( sel $end
$var wire 1 J w1 $end
$var wire 1 K w2 $end
$var wire 1 L y $end
$upscope $end
$scope module m6 $end
$var wire 1 M in0 $end
$var wire 1 N in1 $end
$var wire 1 O nsel $end
$var wire 1 ( sel $end
$var wire 1 P w1 $end
$var wire 1 Q w2 $end
$var wire 1 R y $end
$upscope $end
$scope module m7 $end
$var wire 1 S in0 $end
$var wire 1 T in1 $end
$var wire 1 U nsel $end
$var wire 1 ( sel $end
$var wire 1 V w1 $end
$var wire 1 W w2 $end
$var wire 1 X y $end
$upscope $end
$upscope $end
$upscope $end
$enddefinitions $end
#0
$dumpvars
xX
xW
xV
xU
xT
xS
xR
xQ
xP
xO
xN
xM
xL
xK
xJ
xI
xH
xG
xF
xE
xD
xC
xB
xA
bx @
bx ?
bx >
0=
0<
0;
1:
19
08
17
06
15
14
03
12
01
00
0/
1.
1-
0,
b10 +
b101 *
b10 )
x(
0'
bx &
b101 %
bx $
b10 #
b10 "
bx !
$end
#10000
07
11
05
b101 "
b101 +
1=
0.
10
04
0:
1<
1'
#20000
b111 "
b111 +
17
15
1/
1;
1.
00
14
1:
0<
0-
09
1,
18
0'
b0 %
b0 *
b111 #
b111 )
#30000
01
b100 "
b100 +
07
0/
05
1-
19
0,
02
b101 %
b101 *
b100 #
b100 )
#40000
b110 "
b110 +
17
0;
0.
04
16
0:
1<
0-
13
1,
08
1'
b110 %
b110 *
b1 #
b1 )
#50000
11
b11 "
b11 +
0=
10
0<
1-
09
0,
12
b11 %
b11 *
b10 #
b10 )
#60000
0F
1L
0R
b1010 !
b1010 @
1X
0D
1J
0P
1V
1C
0E
1I
0K
1O
0Q
1U
0W
1B
1H
1N
0T
0A
1G
0M
1S
0(
b111 &
b111 ?
b1010 $
b1010 >
#70000
0L
b1001 !
b1001 @
1F
0J
0V
0C
1E
0I
0O
0U
1W
0H
0N
1T
1M
0S
1(
b1001 &
b1001 ?
b110 $
b110 >
#80000
1L
1R
1J
1P
b111 !
b111 @
0X
1D
1C
0E
1I
1O
1U
0W
0B
1N
0T
1A
0(
b100 &
b100 ?
b111 $
b111 >
#90000
0F
0L
b1100 !
b1100 @
1X
0D
0J
1V
1B
1T
0A
0G
1S
b1101 &
b1101 ?
b1100 $
b1100 >
#100000
b1110 !
b1110 @
1L
0P
0V
0C
0I
1K
0O
1Q
0U
1W
0B
1H
1A
0M
0S
1(
b1110 &
b1110 ?
b1 $
b1 >
#110000
1F
0R
b11 !
b11 @
0X
1E
0Q
0W
1B
0N
0T
1M
b11 &
b11 ?
b101 $
b101 >
