Verilog/P4/priority_encoder.v
module p_encoder(input [3:0]A, input E, output [1:0] O, output V);
    buf B1(O[1], E&(A[3]|A[2]));
    buf B2(O[0], E&(A[3]|((~A[2])&A[1])));
    buf B3(V, E&(A[3]|A[2]|A[1]|A[0]));
endmodule

Verilog/P4/tb.v
`include "priority_encoder.v"
module tb;
reg [3:0] A;
reg E;
wire [1:0] O;
wire V;
p_encoder pe(A, E, O, V);
initial begin
    $dumpfile("tb.vcd");
    $dumpvars(0, tb);
    E = 1; A = 4'b0000;
    #10 E=1; A = 4'b0001;
    #10 E=1; A = 4'b0010;
    #10 E=1; A = 4'b0011;
    #10 E=1; A = 4'b0100;
    #10 E=0; A = 4'b0101;
    #10 E=1; A = 4'b0110;
    #10 E=0; A = 4'b0111;
    #10 E=1; A = 4'b1000;
    #10 E=1; A = 4'b1001;
    #10 E=0; A = 4'b1010;
    #10 E=1; A = 4'b1011;
    #10 E=1; A = 4'b1100;
    #10 $finish;
end
initial begin
    $monitor("Time = %0t, E = %b, A = %b, O = %b, V = %b", $time, E, A, O, V);
end
endmodule

Verilog/P4/tb.vcd
$date
	Tue Sep 16 22:51:47 2025
$end
$version
	Icarus Verilog
$end
$timescale
	1s
$end
$scope module tb $end
$var wire 1 ! V $end
$var wire 2 " O [1:0] $end
$var reg 4 # A [3:0] $end
$var reg 1 $ E $end
$scope module pe $end
$var wire 4 % A [3:0] $end
$var wire 1 $ E $end
$var wire 1 ! V $end
$var wire 2 & O [1:0] $end
$upscope $end
$upscope $end
$enddefinitions $end
$comment Show the parameter values. $end
$dumpall
$end
#0
$dumpvars
b0 &
b0 %
1$
b0 #
b0 "
0!
$end
#10
1!
b1 #
b1 %
#20
b1 "
b1 &
1!
b10 #
b10 %
#30
b11 #
b11 %
#40
1!
b10 "
b10 &
b100 #
b100 %
#50
b0 "
b0 &
0!
b101 #
b101 %
0$
#60
b10 "
b10 &
1!
b110 #
b110 %
1$
#70
b0 "
b0 &
0!
b111 #
b111 %
0$
#80
b11 "
b11 &
1!
b1000 #
b1000 %
1$
#90
b1001 #
b1001 %
#100
b0 "
b0 &
0!
b1010 #
b1010 %
0$
#110
b11 "
b11 &
1!
b1011 #
b1011 %
1$
#120
b1100 #
b1100 %
