Verilog/L8/src/button_sync.v
module button_sync(
    input   clk, 
    input   in, 
    output  out
);
    reg r1, r2, r3;
    always @(posedge clk) begin
        r1 <= in;
        r2 <= r1;
        r3 <= r2;
        /*< WRITE YOUR CODE HERE >*/
    end
    assign out = (~r3)&r2;
endmodule

Verilog/L8/tb/tb_button_sync.v
`include "src/button_sync.v"

module tb_button_sync;
    // inputs
    reg clk;
    reg in;
    
    // output
    wire out;
    
    button_sync bs_dut (clk, in, out);
    
    // clock generation
    always #5 clk = ~clk; // 10ns clock period
    
    initial begin
        $dumpfile("public/vcd/tb_button_sync.vcd");
        $dumpvars(0, bs_dut);
        
        clk = 0;
        in = 0;
        
        $display("\nTesting button synchronizer.\n");
        $display("|%-9s|%-5s|%-9s|%-9s|",
            "Time", "clk", "in", "out");
        $display("|---------|-----|---------|---------|");
        $monitor("|%-9t|%-5b|%-9b|%-9b|",
            $time, clk, in, out);
        
        // test 1
        in = 0; #20;
        in = 1; #20;
        in = 0; #20;
        $monitoroff;
        if (!out) $display("\n[TEST 1 - PASS]\n");
        else $display("\n[TEST 1 - FAIL]\n");
        $monitoron;
        $display("|%-9s|%-5s|%-9s|%-9s|",
            "Time", "clk", "in", "out");
        $display("|---------|-----|---------|---------|");
        
        // test 2
        in = 0; #10;
        in = 1; #1; 
        in = 0; #1;  
        in = 1; #1;  
        in = 0; #1;  
        in = 1; #16; 
        in = 0; #20;
        $monitoroff;
        $display("\n[TEST 2 - PASS]\n");
        $monitoron;
        $display("|%-9s|%-5s|%-9s|%-9s|",
            "Time", "clk", "in", "out");
        $display("|---------|-----|---------|---------|");
        
        // test 3
        in = 0; #10;
        in = 1; #50;
        in = 0; #20;
        $monitoroff;
        if (!out) $display("\n[TEST 3 - PASS]\n");
        else $display("\n[TEST 3 - FAIL]\n");
        $monitoron;
        $display("|%-9s|%-5s|%-9s|%-9s|",
            "Time", "clk", "in", "out");
        $display("|---------|-----|---------|---------|");
        
        // test 4
        in = 0; #10;
        in = 1; #2; 
        in = 0; #2; 
        in = 1; #2;
        in = 0; #2;
        in = 1; #2;
        in = 0; #20;
        $monitoroff;
        if (!out) $display("\n[TEST 4 - PASS]\n");
        else $display("\n[TEST 4 - FAIL]\n");
        $monitoron;
        $display("|%-9s|%-5s|%-9s|%-9s|",
            "Time", "clk", "in", "out");
        $display("|---------|-----|---------|---------|");
        
        // test 5
        in = 0; #10; 
        in = 1; #20; 
        in = 0; #1;  
        in = 1; #1;  
        in = 0; #1;  
        in = 1; #1;  
        in = 0; #16; 
        $monitoroff;
        if (!out) $display("\n[TEST 5 - PASS]\n");
        else $display("\n[TEST 5 - FAIL]\n");
        
        #20;
        $finish;
    end
    
endmodule

Verilog/L8/public/vcd/tb_button_sync.vcd
$date
	Wed Oct 15 15:01:31 2025
$end
$version
	Icarus Verilog
$end
$timescale
	1s
$end
$scope module tb_button_sync $end
$scope module bs_dut $end
$var wire 1 ! clk $end
$var wire 1 " in $end
$var wire 1 # out $end
$var reg 1 $ r1 $end
$var reg 1 % r2 $end
$var reg 1 & r3 $end
$upscope $end
$upscope $end
$enddefinitions $end
#0
$dumpvars
x&
x%
x$
x#
0"
0!
$end
#5
0$
1!
#10
0!
#15
0#
0%
1!
#20
0!
1"
#25
0&
1$
1!
#30
0!
#35
1#
1%
1!
#40
0!
0"
#45
0#
1&
0$
1!
#50
0!
#55
0%
1!
#60
0!
#65
0&
1!
#70
0!
1"
#71
0"
#72
1"
#73
0"
#74
1"
#75
1$
1!
#80
0!
#85
1#
1%
1!
#90
0!
0"
#95
0#
1&
0$
1!
#100
0!
#105
0%
1!
#110
0!
#115
0&
1!
#120
0!
1"
#125
1$
1!
#130
0!
#135
1#
1%
1!
#140
0!
#145
0#
1&
1!
#150
0!
#155
1!
#160
0!
#165
1!
#170
0!
0"
#175
0$
1!
#180
0!
#185
0%
1!
#190
0!
#195
0&
1!
#200
0!
1"
#202
0"
#204
1"
#205
1$
1!
#206
0"
#208
1"
#210
0"
0!
#215
1#
1%
0$
1!
#220
0!
#225
0#
1&
0%
1!
#230
0!
#235
0&
1!
#240
0!
1"
#245
1$
1!
#250
0!
#255
1#
1%
1!
#260
0!
0"
#261
1"
#262
0"
#263
1"
#264
0"
#265
0#
1&
0$
1!
#270
0!
#275
0%
1!
#280
0!
#285
0&
1!
