Verilog/L8/src/button_sync.v
module button_sync(
    input   clk, 
    input   in, 
    output  out
);
    reg r1, r2, r3;
    always @(posedge clk) begin
        r1 <= in;
        r2 <= r1;
        r3 <= r2;
        /*< WRITE YOUR CODE HERE >*/
    end
    assign out = (~r3)&r2;
endmodule

Verilog/L8/src/lock.v
`include "src/button_sync.v"

module lock(
    input       clk, 
    input       reset_in, 
    input       b0_in, 
    input       b1_in, 
    output reg  unlock
);
    
    // synchronize push buttons, convert to pulses
    wire reset, b0, b1; 
    button_sync b_reset(clk, reset_in, reset);
    button_sync b_0(clk, b0_in, b0);
    button_sync b_1(clk, b1_in, b1);

    // b0 corresponds to transition 0, b1 corresponds to transition 1

    /* 
    steps:
    1. declare parameters for states
    2. declare state registers called 'state' and 'next_state'
    3. sequential always block for reset and state update
    4. combinational always block for FSM logic
    */
    
    /*< WRITE YOUR CODE HERE >*/
    parameter[2:0] S0=3'b000, S1=3'b001, S2=3'b010, S3=3'b011, S4=3'b100, S5=3'b101;
    reg[2:0] state, next_state;
    // sequential block
    always @(posedge clk) begin
        if(reset) state <= S0;
        else state <= next_state;
        /*< WRITE YOUR CODE HERE >*/

    end

    // combinational block
    always @(*) begin
        next_state = state; // if no input, stay in current state by default, don't remove this
        
        case (state)
            S0: begin
                unlock=0;
                if(b0) next_state = S1;
                else if(b1) next_state = S0;
            end
            S1: begin
                unlock=0;
                if(b0) next_state = S1;
                else if(b1) next_state = S2;                
            end
            S2: begin
                unlock=0;
                if(b0) next_state = S3;
                else if(b1) next_state = S0;               
            end
            S3: begin
                unlock=0;
                if(b0) next_state = S1;
                else if(b1) next_state = S4;               
            end
            S4: begin
                unlock=0;
                if(b0) next_state = S3;
                else if(b1) next_state = S5;               
            end
            S5: begin
                unlock=1;
                if(b0) next_state = S1;
                else if(b1) next_state = S0;       
            end
            default: next_state = S0;
        endcase

    end

endmodule

Verilog/L8/tb/tb_lock.v
`include "src/lock.v"

module tb_lock;
    // inputs
    reg clk;
    reg reset_in;
    reg b0_in;
    reg b1_in;
    
    // output
    wire unlock;
    
    lock lock_dut (
        .clk(clk),
        .reset_in(reset_in),
        .b0_in(b0_in),
        .b1_in(b1_in),
        .unlock(unlock)
    );
    
    // clock generation
    always #5 clk = ~clk; // 10ns clock period
    
    // button press
    task press_button;
        input button;
        begin
            if (button == 0) begin
                b0_in = 1; #20; b0_in = 0; #40;
            end else begin
                b1_in = 1; #20; b1_in = 0; #40;
            end
        end
    endtask
    
    initial begin
        $dumpfile("public/vcd/tb_lock.vcd");
        $dumpvars(0, lock_dut);
        
        clk = 0;
        reset_in = 0;
        b0_in = 0;
        b1_in = 0;
        
        $display("\nTesting electronic combination lock.\n");
        $display("|%-9s|%-5s|%-9s|%-9s|%-9s|%-9s|",
            "Time", "clk", "reset", "b0_in", "b1_in", "unlock");
        $display("|---------|-----|---------|---------|---------|---------|");
        $monitor("|%-9t|%-5b|%-9b|%-9b|%-9b|%-9b|",
            $time, clk, reset_in, b0_in, b1_in, unlock);
        
        // test 1
        reset_in = 1; #20; reset_in = 0; #20;
        press_button(0);
        press_button(1);
        press_button(0);
        press_button(1);
        press_button(1);
        #20;
        $monitoroff;
        if (unlock) $display("\n[TEST 1 - Sequence:01011 - PASS]\n");
        else $display("\n[TEST 1 - Sequence:01011 - FAIL]\n");
        $monitoron;
        $display("|%-9s|%-5s|%-9s|%-9s|%-9s|%-9s|",
            "Time", "clk", "reset", "b0_in", "b1_in", "unlock");
        $display("|---------|-----|---------|---------|---------|---------|");
        
        // test 2
        reset_in = 1; #20; reset_in = 0; #20;
        press_button(0);
        press_button(1);
        press_button(0);
        press_button(1);
        press_button(0);
        #20;
        $monitoroff;
        if (!unlock) $display("\n[TEST 2 - Sequence:01010 - PASS]\n");
        else $display("\n[TEST 2 - Sequence:01010 - FAIL]\n");
        $monitoron;
        $display("|%-9s|%-5s|%-9s|%-9s|%-9s|%-9s|",
            "Time", "clk", "reset", "b0_in", "b1_in", "unlock");
        $display("|---------|-----|---------|---------|---------|---------|");
        
        // test 3
        reset_in = 1; #20; reset_in = 0; #20;
        press_button(1);
        press_button(1);
        press_button(1);
        press_button(1);
        press_button(1);
        #20;
        $monitoroff;
        if (!unlock) $display("\n[TEST 3 - Sequence:11111 - PASS]\n");
        else $display("\n[TEST 3 - Sequence:11111 - FAIL]\n");
        $monitoron;
        $display("|%-9s|%-5s|%-9s|%-9s|%-9s|%-9s|",
            "Time", "clk", "reset", "b0_in", "b1_in", "unlock");
        $display("|---------|-----|---------|---------|---------|---------|");
        
        // test 4
        reset_in = 1; #20; reset_in = 0; #20;
        press_button(0);
        press_button(0);  
        press_button(1);
        press_button(0);
        press_button(1);
        press_button(1);
        #20;
        $monitoroff;
        if (unlock) $display("\n[TEST 4 - Sequence:001011 - PASS]\n");
        else $display("\n[TEST 4 - Sequence:001011 - FAIL]\n");
        $monitoron;
        $display("|%-9s|%-5s|%-9s|%-9s|%-9s|%-9s|",
            "Time", "clk", "reset", "b0_in", "b1_in", "unlock");
        $display("|---------|-----|---------|---------|---------|---------|");
        
        // test 5
        reset_in = 1; #20; reset_in = 0; #20;
        press_button(0);
        press_button(0);
        press_button(0);
        press_button(0);
        press_button(0);
        #20;
        $monitoroff;
        if (!unlock) $display("\n[TEST 5 - Sequence:00000 - PASS]\n");
        else $display("\n[TEST 5 - Sequence:00000 - FAIL]\n");
        $monitoron;
        $display("|%-9s|%-5s|%-9s|%-9s|%-9s|%-9s|",
            "Time", "clk", "reset", "b0_in", "b1_in", "unlock");
        $display("|---------|-----|---------|---------|---------|---------|");
        
        // test 6
        reset_in = 1; #20; reset_in = 0; #20;
        press_button(0);
        press_button(1);
        press_button(0);
        press_button(0);
        press_button(1);
        #20;
        $monitoroff;
        if (!unlock) $display("\n[TEST 6 - Sequence:01001 - PASS]\n");
        else $display("\n[TEST 6 - Sequence:01001 - FAIL]\n");
        $monitoron;
        $display("|%-9s|%-5s|%-9s|%-9s|%-9s|%-9s|",
            "Time", "clk", "reset", "b0_in", "b1_in", "unlock");
        $display("|---------|-----|---------|---------|---------|---------|");
        
        // test 7
        reset_in = 1; #20; reset_in = 0; #20;
        press_button(0);
        press_button(1);
        press_button(0);
        press_button(1);
        press_button(1);
        #20;
        $monitoroff;
        if (unlock) $display("\n[TEST 7 - Sequence:010110110 - PASS]\n");
        else $display("\n[TEST 7 - Sequence:010110110 - FAIL]\n");
        $monitoron;
        $display("|%-9s|%-5s|%-9s|%-9s|%-9s|%-9s|",
            "Time", "clk", "reset", "b0_in", "b1_in", "unlock");
        $display("|---------|-----|---------|---------|---------|---------|");
        
        // remaining 0110 from test 7
        press_button(0);
        press_button(1);
        press_button(1);
        press_button(0);

        // test 8
        reset_in = 1; #20; reset_in = 0; #20;
        press_button(1); 
        press_button(0);
        press_button(1);
        press_button(0);
        press_button(1);
        press_button(0);
        press_button(1);
        press_button(1);
        #20;
        $monitoroff;
        if (unlock) $display("\n[TEST 8 - Sequence:10101011 - PASS]\n");
        else $display("\n[TEST 8 - Sequence:10101011 - FAIL]\n");
        $monitoron;
        $display("|%-9s|%-5s|%-9s|%-9s|%-9s|%-9s|",
            "Time", "clk", "reset", "b0_in", "b1_in", "unlock");
        $display("|---------|-----|---------|---------|---------|---------|");
        
        // test 9
        reset_in = 1; #20; reset_in = 0; #20;
        press_button(0); 
        press_button(1); 
        press_button(0); 
        press_button(0);
        press_button(1); 
        #20;
        $monitoroff;
        if (!unlock) $display("\n[TEST 9 - Sequence:01001 - PASS]\n");
        else $display("\n[TEST 9 - Sequence:01001 - FAIL]\n");
        $monitoron;
        $display("|%-9s|%-5s|%-9s|%-9s|%-9s|%-9s|",
            "Time", "clk", "reset", "b0_in", "b1_in", "unlock");
        $display("|---------|-----|---------|---------|---------|---------|");
        
        // test 10
        reset_in = 1; #20; reset_in = 0; #20;
        press_button(1); 
        press_button(1); 
        press_button(1); 
        press_button(1); 
        press_button(1); 
        #20;
        $monitoroff;
        if (!unlock) $display("\n[TEST 10 - Sequence:11111 - PASS]\n");
        else $display("\n[TEST 10 - Sequence:11111 - FAIL]\n");
        
        #20;
        $finish;
    end
    
endmodule

Verilog/L8/public/vcd/tb_lock.vcd
$date
	Wed Oct 15 15:01:32 2025
$end
$version
	Icarus Verilog
$end
$timescale
	1s
$end
$scope module tb_lock $end
$scope module lock_dut $end
$var wire 1 ! b0_in $end
$var wire 1 " b1_in $end
$var wire 1 # clk $end
$var wire 1 $ reset_in $end
$var wire 1 % reset $end
$var wire 1 & b1 $end
$var wire 1 ' b0 $end
$var reg 3 ( next_state [2:0] $end
$var reg 3 ) state [2:0] $end
$var reg 1 * unlock $end
$scope module b_0 $end
$var wire 1 # clk $end
$var wire 1 ! in $end
$var wire 1 ' out $end
$var reg 1 + r1 $end
$var reg 1 , r2 $end
$var reg 1 - r3 $end
$upscope $end
$scope module b_1 $end
$var wire 1 # clk $end
$var wire 1 " in $end
$var wire 1 & out $end
$var reg 1 . r1 $end
$var reg 1 / r2 $end
$var reg 1 0 r3 $end
$upscope $end
$scope module b_reset $end
$var wire 1 # clk $end
$var wire 1 $ in $end
$var wire 1 % out $end
$var reg 1 1 r1 $end
$var reg 1 2 r2 $end
$var reg 1 3 r3 $end
$upscope $end
$upscope $end
$upscope $end
$enddefinitions $end
#0
$dumpvars
x3
x2
x1
x0
x/
x.
x-
x,
x+
x*
bx )
bx (
x'
x&
x%
1$
0#
0"
0!
$end
#5
11
0+
0.
1#
#10
0#
#15
b0 (
0&
0'
0/
0,
12
1#
#20
0#
0$
#25
0%
0*
13
01
0-
00
b0 )
1#
#30
0#
#35
02
1#
#40
0#
1!
#45
03
1+
1#
#50
0#
#55
b1 (
1'
1,
1#
#60
0#
0!
#65
0'
1-
0+
b1 )
1#
#70
0#
#75
0,
1#
#80
0#
#85
0-
1#
#90
0#
#95
1#
#100
0#
1"
#105
1.
1#
#110
0#
#115
b10 (
1&
1/
1#
#120
0#
0"
#125
0&
b10 (
10
0.
b10 )
1#
#130
0#
#135
0/
1#
#140
0#
#145
00
1#
#150
0#
#155
1#
#160
0#
1!
#165
1+
1#
#170
0#
#175
b11 (
1'
1,
1#
#180
0#
0!
#185
0'
b11 (
1-
0+
b11 )
1#
#190
0#
#195
0,
1#
#200
0#
#205
0-
1#
#210
0#
#215
1#
#220
0#
1"
#225
1.
1#
#230
0#
#235
b100 (
1&
1/
1#
#240
0#
0"
#245
0&
b100 (
10
0.
b100 )
1#
#250
0#
#255
0/
1#
#260
0#
#265
00
1#
#270
0#
#275
1#
#280
0#
1"
#285
1.
1#
#290
0#
#295
b101 (
1&
1/
1#
#300
0#
0"
#305
0&
b101 (
1*
10
0.
b101 )
1#
#310
0#
#315
0/
1#
#320
0#
#325
00
1#
#330
0#
#335
1#
#340
0#
#345
1#
#350
0#
#355
1#
#360
0#
1$
#365
11
1#
#370
0#
#375
1%
12
1#
#380
0#
0$
#385
0%
0*
b0 (
13
01
b0 )
1#
#390
0#
#395
02
1#
#400
0#
1!
#405
03
1+
1#
#410
0#
#415
b1 (
1'
1,
1#
#420
0#
0!
#425
0'
1-
0+
b1 )
1#
#430
0#
#435
0,
1#
#440
0#
#445
0-
1#
#450
0#
#455
1#
#460
0#
1"
#465
1.
1#
#470
0#
#475
b10 (
1&
1/
1#
#480
0#
0"
#485
0&
b10 (
10
0.
b10 )
1#
#490
0#
#495
0/
1#
#500
0#
#505
00
1#
#510
0#
#515
1#
#520
0#
1!
#525
1+
1#
#530
0#
#535
b11 (
1'
1,
1#
#540
0#
0!
#545
0'
b11 (
1-
0+
b11 )
1#
#550
0#
#555
0,
1#
#560
0#
#565
0-
1#
#570
0#
#575
1#
#580
0#
1"
#585
1.
1#
#590
0#
#595
b100 (
1&
1/
1#
#600
0#
0"
#605
0&
b100 (
10
0.
b100 )
1#
#610
0#
#615
0/
1#
#620
0#
#625
00
1#
#630
0#
#635
1#
#640
0#
1!
#645
1+
1#
#650
0#
#655
b11 (
1'
1,
1#
#660
0#
0!
#665
0'
b11 (
1-
0+
b11 )
1#
#670
0#
#675
0,
1#
#680
0#
#685
0-
1#
#690
0#
#695
1#
#700
0#
#705
1#
#710
0#
#715
1#
#720
0#
1$
#725
11
1#
#730
0#
#735
1%
12
1#
#740
0#
0$
#745
0%
b0 (
13
01
b0 )
1#
#750
0#
#755
02
1#
#760
0#
1"
#765
03
1.
1#
#770
0#
#775
1&
1/
1#
#780
0#
0"
#785
0&
10
0.
1#
#790
0#
#795
0/
1#
#800
0#
#805
00
1#
#810
0#
#815
1#
#820
0#
1"
#825
1.
1#
#830
0#
#835
1&
1/
1#
#840
0#
0"
#845
0&
10
0.
1#
#850
0#
#855
0/
1#
#860
0#
#865
00
1#
#870
0#
#875
1#
#880
0#
1"
#885
1.
1#
#890
0#
#895
1&
1/
1#
#900
0#
0"
#905
0&
10
0.
1#
#910
0#
#915
0/
1#
#920
0#
#925
00
1#
#930
0#
#935
1#
#940
0#
1"
#945
1.
1#
#950
0#
#955
1&
1/
1#
#960
0#
0"
#965
0&
10
0.
1#
#970
0#
#975
0/
1#
#980
0#
#985
00
1#
#990
0#
#995
1#
#1000
0#
1"
#1005
1.
1#
#1010
0#
#1015
1&
1/
1#
#1020
0#
0"
#1025
0&
10
0.
1#
#1030
0#
#1035
0/
1#
#1040
0#
#1045
00
1#
#1050
0#
#1055
1#
#1060
0#
#1065
1#
#1070
0#
#1075
1#
#1080
0#
1$
#1085
11
1#
#1090
0#
#1095
1%
12
1#
#1100
0#
0$
#1105
0%
13
01
1#
#1110
0#
#1115
02
1#
#1120
0#
1!
#1125
03
1+
1#
#1130
0#
#1135
b1 (
1'
1,
1#
#1140
0#
0!
#1145
0'
1-
0+
b1 )
1#
#1150
0#
#1155
0,
1#
#1160
0#
#1165
0-
1#
#1170
0#
#1175
1#
#1180
0#
1!
#1185
1+
1#
#1190
0#
#1195
1'
1,
1#
#1200
0#
0!
#1205
0'
1-
0+
1#
#1210
0#
#1215
0,
1#
#1220
0#
#1225
0-
1#
#1230
0#
#1235
1#
#1240
0#
1"
#1245
1.
1#
#1250
0#
#1255
b10 (
1&
1/
1#
#1260
0#
0"
#1265
0&
b10 (
10
0.
b10 )
1#
#1270
0#
#1275
0/
1#
#1280
0#
#1285
00
1#
#1290
0#
#1295
1#
#1300
0#
1!
#1305
1+
1#
#1310
0#
#1315
b11 (
1'
1,
1#
#1320
0#
0!
#1325
0'
b11 (
1-
0+
b11 )
1#
#1330
0#
#1335
0,
1#
#1340
0#
#1345
0-
1#
#1350
0#
#1355
1#
#1360
0#
1"
#1365
1.
1#
#1370
0#
#1375
b100 (
1&
1/
1#
#1380
0#
0"
#1385
0&
b100 (
10
0.
b100 )
1#
#1390
0#
#1395
0/
1#
#1400
0#
#1405
00
1#
#1410
0#
#1415
1#
#1420
0#
1"
#1425
1.
1#
#1430
0#
#1435
b101 (
1&
1/
1#
#1440
0#
0"
#1445
0&
b101 (
1*
10
0.
b101 )
1#
#1450
0#
#1455
0/
1#
#1460
0#
#1465
00
1#
#1470
0#
#1475
1#
#1480
0#
#1485
1#
#1490
0#
#1495
1#
#1500
0#
1$
#1505
11
1#
#1510
0#
#1515
1%
12
1#
#1520
0#
0$
#1525
0%
0*
b0 (
13
01
b0 )
1#
#1530
0#
#1535
02
1#
#1540
0#
1!
#1545
03
1+
1#
#1550
0#
#1555
b1 (
1'
1,
1#
#1560
0#
0!
#1565
0'
1-
0+
b1 )
1#
#1570
0#
#1575
0,
1#
#1580
0#
#1585
0-
1#
#1590
0#
#1595
1#
#1600
0#
1!
#1605
1+
1#
#1610
0#
#1615
1'
1,
1#
#1620
0#
0!
#1625
0'
1-
0+
1#
#1630
0#
#1635
0,
1#
#1640
0#
#1645
0-
1#
#1650
0#
#1655
1#
#1660
0#
1!
#1665
1+
1#
#1670
0#
#1675
1'
1,
1#
#1680
0#
0!
#1685
0'
1-
0+
1#
#1690
0#
#1695
0,
1#
#1700
0#
#1705
0-
1#
#1710
0#
#1715
1#
#1720
0#
1!
#1725
1+
1#
#1730
0#
#1735
1'
1,
1#
#1740
0#
0!
#1745
0'
1-
0+
1#
#1750
0#
#1755
0,
1#
#1760
0#
#1765
0-
1#
#1770
0#
#1775
1#
#1780
0#
1!
#1785
1+
1#
#1790
0#
#1795
1'
1,
1#
#1800
0#
0!
#1805
0'
1-
0+
1#
#1810
0#
#1815
0,
1#
#1820
0#
#1825
0-
1#
#1830
0#
#1835
1#
#1840
0#
#1845
1#
#1850
0#
#1855
1#
#1860
0#
1$
#1865
11
1#
#1870
0#
#1875
1%
12
1#
#1880
0#
0$
#1885
0%
b0 (
13
01
b0 )
1#
#1890
0#
#1895
02
1#
#1900
0#
1!
#1905
03
1+
1#
#1910
0#
#1915
b1 (
1'
1,
1#
#1920
0#
0!
#1925
0'
1-
0+
b1 )
1#
#1930
0#
#1935
0,
1#
#1940
0#
#1945
0-
1#
#1950
0#
#1955
1#
#1960
0#
1"
#1965
1.
1#
#1970
0#
#1975
b10 (
1&
1/
1#
#1980
0#
0"
#1985
0&
b10 (
10
0.
b10 )
1#
#1990
0#
#1995
0/
1#
#2000
0#
#2005
00
1#
#2010
0#
#2015
1#
#2020
0#
1!
#2025
1+
1#
#2030
0#
#2035
b11 (
1'
1,
1#
#2040
0#
0!
#2045
0'
b11 (
1-
0+
b11 )
1#
#2050
0#
#2055
0,
1#
#2060
0#
#2065
0-
1#
#2070
0#
#2075
1#
#2080
0#
1!
#2085
1+
1#
#2090
0#
#2095
b1 (
1'
1,
1#
#2100
0#
0!
#2105
0'
1-
0+
b1 )
1#
#2110
0#
#2115
0,
1#
#2120
0#
#2125
0-
1#
#2130
0#
#2135
1#
#2140
0#
1"
#2145
1.
1#
#2150
0#
#2155
b10 (
1&
1/
1#
#2160
0#
0"
#2165
0&
b10 (
10
0.
b10 )
1#
#2170
0#
#2175
0/
1#
#2180
0#
#2185
00
1#
#2190
0#
#2195
1#
#2200
0#
#2205
1#
#2210
0#
#2215
1#
#2220
0#
1$
#2225
11
1#
#2230
0#
#2235
1%
12
1#
#2240
0#
0$
#2245
0%
b0 (
13
01
b0 )
1#
#2250
0#
#2255
02
1#
#2260
0#
1!
#2265
03
1+
1#
#2270
0#
#2275
b1 (
1'
1,
1#
#2280
0#
0!
#2285
0'
1-
0+
b1 )
1#
#2290
0#
#2295
0,
1#
#2300
0#
#2305
0-
1#
#2310
0#
#2315
1#
#2320
0#
1"
#2325
1.
1#
#2330
0#
#2335
b10 (
1&
1/
1#
#2340
0#
0"
#2345
0&
b10 (
10
0.
b10 )
1#
#2350
0#
#2355
0/
1#
#2360
0#
#2365
00
1#
#2370
0#
#2375
1#
#2380
0#
1!
#2385
1+
1#
#2390
0#
#2395
b11 (
1'
1,
1#
#2400
0#
0!
#2405
0'
b11 (
1-
0+
b11 )
1#
#2410
0#
#2415
0,
1#
#2420
0#
#2425
0-
1#
#2430
0#
#2435
1#
#2440
0#
1"
#2445
1.
1#
#2450
0#
#2455
b100 (
1&
1/
1#
#2460
0#
0"
#2465
0&
b100 (
10
0.
b100 )
1#
#2470
0#
#2475
0/
1#
#2480
0#
#2485
00
1#
#2490
0#
#2495
1#
#2500
0#
1"
#2505
1.
1#
#2510
0#
#2515
b101 (
1&
1/
1#
#2520
0#
0"
#2525
0&
b101 (
1*
10
0.
b101 )
1#
#2530
0#
#2535
0/
1#
#2540
0#
#2545
00
1#
#2550
0#
#2555
1#
#2560
0#
#2565
1#
#2570
0#
#2575
1#
#2580
0#
1!
#2585
1+
1#
#2590
0#
#2595
b1 (
1'
1,
1#
#2600
0#
0!
#2605
0'
0*
1-
0+
b1 )
1#
#2610
0#
#2615
0,
1#
#2620
0#
#2625
0-
1#
#2630
0#
#2635
1#
#2640
0#
1"
#2645
1.
1#
#2650
0#
#2655
b10 (
1&
1/
1#
#2660
0#
0"
#2665
0&
b10 (
10
0.
b10 )
1#
#2670
0#
#2675
0/
1#
#2680
0#
#2685
00
1#
#2690
0#
#2695
1#
#2700
0#
1"
#2705
1.
1#
#2710
0#
#2715
b0 (
1&
1/
1#
#2720
0#
0"
#2725
0&
10
0.
b0 )
1#
#2730
0#
#2735
0/
1#
#2740
0#
#2745
00
1#
#2750
0#
#2755
1#
#2760
0#
1!
#2765
1+
1#
#2770
0#
#2775
b1 (
1'
1,
1#
#2780
0#
0!
#2785
0'
1-
0+
b1 )
1#
#2790
0#
#2795
0,
1#
#2800
0#
#2805
0-
1#
#2810
0#
#2815
1#
#2820
0#
1$
#2825
11
1#
#2830
0#
#2835
1%
12
1#
#2840
0#
0$
#2845
0%
b0 (
13
01
b0 )
1#
#2850
0#
#2855
02
1#
#2860
0#
1"
#2865
03
1.
1#
#2870
0#
#2875
1&
1/
1#
#2880
0#
0"
#2885
0&
10
0.
1#
#2890
0#
#2895
0/
1#
#2900
0#
#2905
00
1#
#2910
0#
#2915
1#
#2920
0#
1!
#2925
1+
1#
#2930
0#
#2935
b1 (
1'
1,
1#
#2940
0#
0!
#2945
0'
1-
0+
b1 )
1#
#2950
0#
#2955
0,
1#
#2960
0#
#2965
0-
1#
#2970
0#
#2975
1#
#2980
0#
1"
#2985
1.
1#
#2990
0#
#2995
b10 (
1&
1/
1#
#3000
0#
0"
#3005
0&
b10 (
10
0.
b10 )
1#
#3010
0#
#3015
0/
1#
#3020
0#
#3025
00
1#
#3030
0#
#3035
1#
#3040
0#
1!
#3045
1+
1#
#3050
0#
#3055
b11 (
1'
1,
1#
#3060
0#
0!
#3065
0'
b11 (
1-
0+
b11 )
1#
#3070
0#
#3075
0,
1#
#3080
0#
#3085
0-
1#
#3090
0#
#3095
1#
#3100
0#
1"
#3105
1.
1#
#3110
0#
#3115
b100 (
1&
1/
1#
#3120
0#
0"
#3125
0&
b100 (
10
0.
b100 )
1#
#3130
0#
#3135
0/
1#
#3140
0#
#3145
00
1#
#3150
0#
#3155
1#
#3160
0#
1!
#3165
1+
1#
#3170
0#
#3175
b11 (
1'
1,
1#
#3180
0#
0!
#3185
0'
b11 (
1-
0+
b11 )
1#
#3190
0#
#3195
0,
1#
#3200
0#
#3205
0-
1#
#3210
0#
#3215
1#
#3220
0#
1"
#3225
1.
1#
#3230
0#
#3235
b100 (
1&
1/
1#
#3240
0#
0"
#3245
0&
b100 (
10
0.
b100 )
1#
#3250
0#
#3255
0/
1#
#3260
0#
#3265
00
1#
#3270
0#
#3275
1#
#3280
0#
1"
#3285
1.
1#
#3290
0#
#3295
b101 (
1&
1/
1#
#3300
0#
0"
#3305
0&
b101 (
1*
10
0.
b101 )
1#
#3310
0#
#3315
0/
1#
#3320
0#
#3325
00
1#
#3330
0#
#3335
1#
#3340
0#
#3345
1#
#3350
0#
#3355
1#
#3360
0#
1$
#3365
11
1#
#3370
0#
#3375
1%
12
1#
#3380
0#
0$
#3385
0%
0*
b0 (
13
01
b0 )
1#
#3390
0#
#3395
02
1#
#3400
0#
1!
#3405
03
1+
1#
#3410
0#
#3415
b1 (
1'
1,
1#
#3420
0#
0!
#3425
0'
1-
0+
b1 )
1#
#3430
0#
#3435
0,
1#
#3440
0#
#3445
0-
1#
#3450
0#
#3455
1#
#3460
0#
1"
#3465
1.
1#
#3470
0#
#3475
b10 (
1&
1/
1#
#3480
0#
0"
#3485
0&
b10 (
10
0.
b10 )
1#
#3490
0#
#3495
0/
1#
#3500
0#
#3505
00
1#
#3510
0#
#3515
1#
#3520
0#
1!
#3525
1+
1#
#3530
0#
#3535
b11 (
1'
1,
1#
#3540
0#
0!
#3545
0'
b11 (
1-
0+
b11 )
1#
#3550
0#
#3555
0,
1#
#3560
0#
#3565
0-
1#
#3570
0#
#3575
1#
#3580
0#
1!
#3585
1+
1#
#3590
0#
#3595
b1 (
1'
1,
1#
#3600
0#
0!
#3605
0'
1-
0+
b1 )
1#
#3610
0#
#3615
0,
1#
#3620
0#
#3625
0-
1#
#3630
0#
#3635
1#
#3640
0#
1"
#3645
1.
1#
#3650
0#
#3655
b10 (
1&
1/
1#
#3660
0#
0"
#3665
0&
b10 (
10
0.
b10 )
1#
#3670
0#
#3675
0/
1#
#3680
0#
#3685
00
1#
#3690
0#
#3695
1#
#3700
0#
#3705
1#
#3710
0#
#3715
1#
#3720
0#
1$
#3725
11
1#
#3730
0#
#3735
1%
12
1#
#3740
0#
0$
#3745
0%
b0 (
13
01
b0 )
1#
#3750
0#
#3755
02
1#
#3760
0#
1"
#3765
03
1.
1#
#3770
0#
#3775
1&
1/
1#
#3780
0#
0"
#3785
0&
10
0.
1#
#3790
0#
#3795
0/
1#
#3800
0#
#3805
00
1#
#3810
0#
#3815
1#
#3820
0#
1"
#3825
1.
1#
#3830
0#
#3835
1&
1/
1#
#3840
0#
0"
#3845
0&
10
0.
1#
#3850
0#
#3855
0/
1#
#3860
0#
#3865
00
1#
#3870
0#
#3875
1#
#3880
0#
1"
#3885
1.
1#
#3890
0#
#3895
1&
1/
1#
#3900
0#
0"
#3905
0&
10
0.
1#
#3910
0#
#3915
0/
1#
#3920
0#
#3925
00
1#
#3930
0#
#3935
1#
#3940
0#
1"
#3945
1.
1#
#3950
0#
#3955
1&
1/
1#
#3960
0#
0"
#3965
0&
10
0.
1#
#3970
0#
#3975
0/
1#
#3980
0#
#3985
00
1#
#3990
0#
#3995
1#
#4000
0#
1"
#4005
1.
1#
#4010
0#
#4015
1&
1/
1#
#4020
0#
0"
#4025
0&
10
0.
1#
#4030
0#
#4035
0/
1#
#4040
0#
#4045
00
1#
