Verilog/T6/solution/FSM.v
module FSM (input clk, input reset, input in, output reg out);
    reg [1:0]state;
    reg [1:0]nextState;
    parameter S0 = 2'b00, S1 = 2'b01, S2 = 2'b10;

    always @(posedge clk, posedge reset) begin
        if(reset) 
            state <= S0;
        else
            state <= nextState;
    end

    always @(state, in) begin
        case (state)
              S0: begin
                if(!in) begin
                    nextState = S0;
                    out = 1'b1;
                end
                else begin
                    nextState = S1;
                    out = 1'b0;
                end
              end
              S1: begin
                if(!in) begin
                    nextState = S1;
                    out = 1'b0;
                end
                else begin
                    nextState = S2;
                    out = 1'b0;
                end
              end
              S2: begin
                if(!in) begin
                    nextState = S2;
                    out = 1'b0;
                end
                else begin
                    nextState = S0;
                    out = 1'b1;
                end
              end
        endcase
    end
endmodule

Verilog/T6/testbench.v
`include "FSM.v" 

module testbench();
    reg clk;
    reg reset;
    reg in;
    wire out;

    FSM f(clk, reset, in, out);
    
    always begin
        #5 clk = ~clk; 
    end

    wire [7:0] state_alias;
    assign state_alias = (f.state == 2'b00) ? "A" : (f.state == 2'b01) ? "B" : (f.state == 2'b10) ? "C" : "D";

    initial begin
        $dumpfile("out.vcd");
        $dumpvars(0, testbench);
        clk = 0; reset = 1; in = 0;

        #10 reset = 0; in = 0;
        #10 in = 1; 
        #10 reset = 1; in = 0; 
        #10 reset = 0; in = 1; 
        #10 in = 1; 
        #20 $finish;
    end

    initial begin
        $monitor("Time = %0t, clk = %b, reset = %b, in = %b, state = %c, out = %b", $time, clk, reset, in, state_alias, out);
    end

endmodule

Verilog/T6/out.vcd
$date
	Wed Oct 15 09:37:36 2025
$end
$version
	Icarus Verilog
$end
$timescale
	1s
$end
$scope module testbench $end
$var wire 8 ! state_alias [7:0] $end
$var wire 1 " out $end
$var reg 1 # clk $end
$var reg 1 $ in $end
$var reg 1 % reset $end
$scope module f $end
$var wire 1 # clk $end
$var wire 1 $ in $end
$var wire 1 % reset $end
$var parameter 2 & S0 $end
$var parameter 2 ' S1 $end
$var parameter 2 ( S2 $end
$var reg 2 ) nextState [1:0] $end
$var reg 1 " out $end
$var reg 2 * state [1:0] $end
$upscope $end
$upscope $end
$enddefinitions $end
$comment Show the parameter values. $end
$dumpall
b10 (
b1 '
b0 &
$end
#0
$dumpvars
b0 *
b0 )
1%
0$
0#
1"
b1000001 !
$end
#5
1#
#10
0#
0%
#15
1#
#20
0"
b1 )
0#
1$
#25
b10 )
b1000010 !
b1 *
1#
#30
1"
b1000001 !
b0 *
b0 )
0#
0$
1%
#35
1#
#40
0"
b1 )
0#
1$
0%
#45
b10 )
b1000010 !
b1 *
1#
#50
0#
#55
b1000011 !
1"
b0 )
b10 *
1#
#60
0#
#65
0"
b1 )
b1000001 !
b0 *
1#
