Verilog/L6/src/full_adder_4bit.v
module full_adder_4bit (
    input  [3:0] A, B,
    output reg [3:0] S
);
    always @(*) begin
        S=A+B;
    end
endmodule

Verilog/L6/tb/tb_full_adder_4bit.v
`include "src/full_adder_4bit.v"

module tb_full_adder_4bit;

    // Inputs
    reg [3:0] A, B;

    // Output
    wire [3:0] S;

    // DUT instantiation
    full_adder_4bit dut (
        .A(A),
        .B(B),
        .S(S)
    );

    initial begin
        $dumpfile("public/vcd/tb_full_adder_4bit.vcd");
        $dumpvars(0, tb_full_adder_4bit);
        
        $display("\nTesting Top Module\n");
        $display("|%-9s|%-9s|%-9s|%-9s|%-9s|%-9s|%-9s|", 
                "Time", "A(bin)", "A(dec)", "B(bin)", "B(dec)", "S(bin)", "S(dec)");
        $display("|---------|---------|---------|---------|---------|---------|---------|");
        $monitor("|%-9t|%-9b|%-9d|%-9b|%-9d|%-9b|%-9d|", 
                $time, A, A, B, B, S, S);

        A = 4'b0000; B = 4'b0000;

        #10 A = 4'b0000; B = 4'b0000;   
        #10 A = 4'b0001; B = 4'b0001; 
        #10 A = 4'b0010; B = 4'b0011; 
        #10 A = 4'b0100; B = 4'b0011; 
        #10 A = 4'b0101; B = 4'b0101;  
        #10 A = 4'b0110; B = 4'b0010; 
        #10 A = 4'b0111; B = 4'b0110;  
        #10 A = 4'b1000; B = 4'b0111;   
        #10 A = 4'b1001; B = 4'b0100;  
        #10 A = 4'b1010; B = 4'b0011;   
        #10 A = 4'b1011; B = 4'b0010;   
        #10 A = 4'b1100; B = 4'b0011;   
        #10 A = 4'b1101; B = 4'b0001;   
        #10 A = 4'b1110; B = 4'b0001;   
        #10 A = 4'b1111; B = 4'b0000;   
        #10 A = 4'b0100; B = 4'b1000;  
        #10 A = 4'b0011; B = 4'b1001;  
        #10 A = 4'b0110; B = 4'b1000;  
        #10 A = 4'b0101; B = 4'b0111;  
        #10 A = 4'b0010; B = 4'b1010;   

        $finish;
    end

endmodule

Verilog/L6/public/vcd/tb_full_adder_4bit.vcd
$date
	Wed Sep 24 15:01:24 2025
$end
$version
	Icarus Verilog
$end
$timescale
	1s
$end
$scope module tb_full_adder_4bit $end
$var wire 4 ! S [3:0] $end
$var reg 4 " A [3:0] $end
$var reg 4 # B [3:0] $end
$scope module dut $end
$var wire 4 $ A [3:0] $end
$var wire 4 % B [3:0] $end
$var reg 4 & S [3:0] $end
$upscope $end
$upscope $end
$enddefinitions $end
#0
$dumpvars
b0 &
b0 %
b0 $
b0 #
b0 "
b0 !
$end
#20
b10 !
b10 &
b1 #
b1 %
b1 "
b1 $
#30
b101 !
b101 &
b11 #
b11 %
b10 "
b10 $
#40
b111 !
b111 &
b100 "
b100 $
#50
b1010 !
b1010 &
b101 #
b101 %
b101 "
b101 $
#60
b1000 !
b1000 &
b10 #
b10 %
b110 "
b110 $
#70
b1101 !
b1101 &
b110 #
b110 %
b111 "
b111 $
#80
b1111 !
b1111 &
b111 #
b111 %
b1000 "
b1000 $
#90
b1101 !
b1101 &
b100 #
b100 %
b1001 "
b1001 $
#100
b11 #
b11 %
b1010 "
b1010 $
#110
b10 #
b10 %
b1011 "
b1011 $
#120
b1111 !
b1111 &
b11 #
b11 %
b1100 "
b1100 $
#130
b1110 !
b1110 &
b1 #
b1 %
b1101 "
b1101 $
#140
b1111 !
b1111 &
b1110 "
b1110 $
#150
b0 #
b0 %
b1111 "
b1111 $
#160
b1100 !
b1100 &
b1000 #
b1000 %
b100 "
b100 $
#170
b1001 #
b1001 %
b11 "
b11 $
#180
b1110 !
b1110 &
b1000 #
b1000 %
b110 "
b110 $
#190
b1100 !
b1100 &
b111 #
b111 %
b101 "
b101 $
#200
b1010 #
b1010 %
b10 "
b10 $
