Verilog/L11/src/register.v
module register(input clk, clear, MSBin, LSBin, S1, S0, input [3:0]D, output reg [3:0]Q);
    always @(posedge clk or posedge clear) begin
        if(clear) Q<=4'b0000;
        else begin
            case({S1, S0})
                2'b01:begin
                    Q<={MSBin,Q[3],Q[2],Q[1]};
                end
                2'b10:begin
                    Q<={Q[2],Q[1],Q[0],LSBin};
                end
                2'b11:begin
                    Q<=D;
                end
            endcase
        end
    end
endmodule

Verilog/L11/src/tb.v
`timescale 1ns/1ps
`include "register.v"

module tb_Q5;

  // DUT signals
  reg        clk;
  reg        clear;      // async active-high
  reg        MSBin;
  reg        LSBin;
  reg        S1, S0;
  reg  [3:0] D;
  wire [3:0] Q;

  // Instantiate DUT
  register dut (
    .clk   (clk),
    .clear (clear),
    .MSBin (MSBin),
    .LSBin (LSBin),
    .S1    (S1),
    .S0    (S0),
    .D     (D),
    .Q     (Q)
  );

  // Clock: 10 time-unit period
  initial clk = 1'b0;
  always #5 clk = ~clk;

  // Waveform dump
  initial begin
    $dumpfile("tb_Q5.vcd");
    $dumpvars(0, tb_Q5);
  end

  // Monitor
  initial begin
    $display(" time | clk | clr   S1  S0 | D    MSB   LSB | Q");
    $monitor("%0d   |  %b | %b   %b  %b | %b    %b    %b | %b",
             $time, clk, clear, S1, S0, D, MSBin, LSBin, Q);
  end

  // Stimulus
  initial begin
    // Defaults
    clear = 1'b1; MSBin = 1'b0; LSBin = 1'b0; S1 = 1'b0; S0 = 1'b0; D = 4'b0000;

    // Release async clear before first posedge
    #5 clear = 1'b0;

    // ----- 1) Parallel load (S1 S0 = 11)
    D = 4'b1010; S1 = 1'b1; S0 = 1'b1; @(posedge clk);  // Q <- 1010

    // ----- 2) No change (S1 S0 = 00)
    S1 = 1'b0; S0 = 1'b0; @(posedge clk);               // Q stays 1010

    // ----- 3) Shift right (S1 S0 = 01), feed MSBin
    S1 = 1'b0; S0 = 1'b1; MSBin = 1'b1; @(posedge clk); // Q <- {1, Q3, Q2, Q1}
    MSBin = 1'b0; @(posedge clk);                       // another shift right

    // ----- 4) Shift left (S1 S0 = 10), feed LSBin
    S1 = 1'b1; S0 = 1'b0; LSBin = 1'b0; @(posedge clk); // Q <- {Q2, Q1, Q0, 0}
    LSBin = 1'b1; @(posedge clk);                       // another shift left with 1

    // ----- 5) Async clear pulse mid-run
    #5 clear = 1'b1; #5 clear = 1'b0;

    // ----- 6) Parallel load again to confirm recovery
    D = 4'b0111; S1 = 1'b1; S0 = 1'b1; @(posedge clk);  // Q <- 0111

    // ----- 7) One of each quickly to touch all again
    S1 = 1'b0; S0 = 1'b0; @(posedge clk);               // no change
    S1 = 1'b0; S0 = 1'b1; MSBin = 1'b1; @(posedge clk); // shift right
    S1 = 1'b1; S0 = 1'b0; LSBin = 1'b0; @(posedge clk); // shift left

    // Done
    #20 $finish;
  end

endmodule

Verilog/L11/src/tb_Q5.vcd
$date
	Wed Nov 12 15:01:55 2025
$end
$version
	Icarus Verilog
$end
$timescale
	1ps
$end
$scope module tb_Q5 $end
$var wire 4 ! Q [3:0] $end
$var reg 4 " D [3:0] $end
$var reg 1 # LSBin $end
$var reg 1 $ MSBin $end
$var reg 1 % S0 $end
$var reg 1 & S1 $end
$var reg 1 ' clear $end
$var reg 1 ( clk $end
$scope module dut $end
$var wire 4 ) D [3:0] $end
$var wire 1 # LSBin $end
$var wire 1 $ MSBin $end
$var wire 1 % S0 $end
$var wire 1 & S1 $end
$var wire 1 ' clear $end
$var wire 1 ( clk $end
$var reg 4 * Q [3:0] $end
$upscope $end
$upscope $end
$enddefinitions $end
#0
$dumpvars
b0 *
b0 )
0(
1'
0&
0%
0$
0#
b0 "
b0 !
$end
#5000
b1010 !
b1010 *
1%
1&
b1010 "
b1010 )
0'
1(
#10000
0(
#15000
0%
0&
1(
#20000
0(
#25000
b1101 !
b1101 *
1$
1%
1(
#30000
0(
#35000
b110 !
b110 *
0$
1(
#40000
0(
#45000
b1100 !
b1100 *
0%
1&
1(
#50000
0(
#55000
b1001 !
b1001 *
1#
1(
#60000
0(
#65000
b11 !
b11 *
1(
#70000
b0 !
b0 *
1'
0(
#75000
b111 !
b111 *
1%
b111 "
b111 )
0'
1(
#80000
0(
#85000
0%
0&
1(
#90000
0(
#95000
b1011 !
b1011 *
1$
1%
1(
#100000
0(
#105000
b110 !
b110 *
0#
0%
1&
1(
#110000
0(
#115000
b1100 !
b1100 *
1(
#120000
0(
#125000
b1000 !
b1000 *
1(
#130000
0(
#135000
b0 !
b0 *
1(
