Verilog/P6/Q3/decoder_5to32.v
// 5-to-32 Decoder (Behavioral)
module decoder5to32 (
    input  wire [4:0] in,      // 5-bit input
    output reg  [31:0] out     // 32-bit one-hot output
);
    /*
    //best way to implement a decoder is using leftshift operation on binary equivalent of 1. However this isnt exactly behavioral modelling
    always @(*) begin
        out = 1 << in; //automatically typecasts from decimal to binary. Instead of simply 1, can also say 32'b1 i.e 0000.....0001
    end
    */

    always @(*) begin
        out = 32'b0; //default //dont use assign, it fixes the out to that value and doesnt let it change
        case(in) 
            0: out[0]=1'b1;
            1: out[1]=1'b1;
            2: out[2]=1'b1;
            3: out[3]=1'b1;
            4: out[4]=1'b1;
            5: out[5]=1'b1;
            6: out[6]=1'b1;
            7: out[7]=1'b1;
            8: out[8]=1'b1;
            9: out[9]=1'b1;
            10: out[10]=1'b1;
            11: out[11]=1'b1;
            12: out[12]=1'b1;
            13: out[13]=1'b1;
            14: out[14]=1'b1;
            15: out[15]=1'b1;
            16: out[16]=1'b1;
            17: out[17]=1'b1;
            18: out[18]=1'b1;
            19: out[19]=1'b1;
            20: out[20]=1'b1;
            21: out[21]=1'b1;
            22: out[22]=1'b1;
            23: out[23]=1'b1;
            24: out[24]=1'b1;
            25: out[25]=1'b1;
            26: out[26]=1'b1;
            27: out[27]=1'b1;
            28: out[28]=1'b1;
            29: out[29]=1'b1;
            30: out[30]=1'b1;
            31: out[31]=1'b1;
        endcase
    end
endmodule

Verilog/P6/Q3/tb_decoder_5to32.v
`include "decoder_5to32.v"
module tb_decoder5to32;

    reg [4:0] in;
    wire [31:0] out;

    // Instantiate the decoder
    decoder5to32 uut (
        .in(in),
        .out(out)
    );

    integer i;

    initial begin
        $dumpfile("decoder5to32_tb.vcd"); // for GTKWave
        $dumpvars(0, tb_decoder5to32);

        $display("Input | One-Hot Output");
        $display("----------------------");

        // Test all 32 possible input values
        for (i = 0; i < 32; i = i + 1) begin
            in = i;
            #5;
            $display("  %2d   | %032b", in, out);
        end

        $finish;
    end

endmodule

Verilog/P6/Q3/decoder5to32_tb.vcd
$date
	Sun Sep 21 17:10:17 2025
$end
$version
	Icarus Verilog
$end
$timescale
	1s
$end
$scope module tb_decoder5to32 $end
$var wire 32 ! out [31:0] $end
$var reg 5 " in [4:0] $end
$var integer 32 # i [31:0] $end
$scope module uut $end
$var wire 5 $ in [4:0] $end
$var reg 32 % out [31:0] $end
$upscope $end
$upscope $end
$enddefinitions $end
$comment Show the parameter values. $end
$dumpall
$end
#0
$dumpvars
b1 %
b0 $
b0 #
b0 "
b1 !
$end
#5
b10 !
b10 %
b1 "
b1 $
b1 #
#10
b100 !
b100 %
b10 "
b10 $
b10 #
#15
b1000 !
b1000 %
b11 "
b11 $
b11 #
#20
b10000 !
b10000 %
b100 "
b100 $
b100 #
#25
b100000 !
b100000 %
b101 "
b101 $
b101 #
#30
b1000000 !
b1000000 %
b110 "
b110 $
b110 #
#35
b10000000 !
b10000000 %
b111 "
b111 $
b111 #
#40
b100000000 !
b100000000 %
b1000 "
b1000 $
b1000 #
#45
b1000000000 !
b1000000000 %
b1001 "
b1001 $
b1001 #
#50
b10000000000 !
b10000000000 %
b1010 "
b1010 $
b1010 #
#55
b100000000000 !
b100000000000 %
b1011 "
b1011 $
b1011 #
#60
b1000000000000 !
b1000000000000 %
b1100 "
b1100 $
b1100 #
#65
b10000000000000 !
b10000000000000 %
b1101 "
b1101 $
b1101 #
#70
b100000000000000 !
b100000000000000 %
b1110 "
b1110 $
b1110 #
#75
b1000000000000000 !
b1000000000000000 %
b1111 "
b1111 $
b1111 #
#80
b10000000000000000 !
b10000000000000000 %
b10000 "
b10000 $
b10000 #
#85
b100000000000000000 !
b100000000000000000 %
b10001 "
b10001 $
b10001 #
#90
b1000000000000000000 !
b1000000000000000000 %
b10010 "
b10010 $
b10010 #
#95
b10000000000000000000 !
b10000000000000000000 %
b10011 "
b10011 $
b10011 #
#100
b100000000000000000000 !
b100000000000000000000 %
b10100 "
b10100 $
b10100 #
#105
b1000000000000000000000 !
b1000000000000000000000 %
b10101 "
b10101 $
b10101 #
#110
b10000000000000000000000 !
b10000000000000000000000 %
b10110 "
b10110 $
b10110 #
#115
b100000000000000000000000 !
b100000000000000000000000 %
b10111 "
b10111 $
b10111 #
#120
b1000000000000000000000000 !
b1000000000000000000000000 %
b11000 "
b11000 $
b11000 #
#125
b10000000000000000000000000 !
b10000000000000000000000000 %
b11001 "
b11001 $
b11001 #
#130
b100000000000000000000000000 !
b100000000000000000000000000 %
b11010 "
b11010 $
b11010 #
#135
b1000000000000000000000000000 !
b1000000000000000000000000000 %
b11011 "
b11011 $
b11011 #
#140
b10000000000000000000000000000 !
b10000000000000000000000000000 %
b11100 "
b11100 $
b11100 #
#145
b100000000000000000000000000000 !
b100000000000000000000000000000 %
b11101 "
b11101 $
b11101 #
#150
b1000000000000000000000000000000 !
b1000000000000000000000000000000 %
b11110 "
b11110 $
b11110 #
#155
b10000000000000000000000000000000 !
b10000000000000000000000000000000 %
b11111 "
b11111 $
b11111 #
#160
b100000 #
