Verilog/L10/src/dff.v
module dff(input clk, input d, input reset, output reg q);
always @(posedge clk) begin
    if(reset) q<=0;
    else q<=d;
end
endmodule

Verilog/L10/tb/tb_dff.v

`include "src/dff.v"

module tb_dff;
    reg clk;
    reg d;
    reg reset;
    wire q;

    dff dut (
        .clk(clk),
        .d(d),
        .reset(reset),
        .q(q)
    );

    always #5 clk = ~clk;

    initial begin
        $dumpfile("public/vcd/tb_dff.vcd");
        $dumpvars(0, dut);

        clk = 0;
        d = 0;
        reset = 0;

        $display("\nTesting D Flip-Flop\n");
        $display("|%-9s|%-5s|%-6s|%-4s|%-4s|", "Time", "clk", "reset", "d", "q");
        $display("|---------|-----|------|----|----|");

        reset = 1; #10;
        $monitor("|%-9t|%-5b|%-6b|%-4b|%-4b|", $time, clk, reset, d, q);
        reset = 0; #10;
        d = 1; #10;
        d = 0; #10;
        d = 1; #20;
        d = 0; #10;
        reset = 1; #10;
        reset = 0; #10;
        d = 1; #10;
        d = 0; #10;

        $monitoroff;
        $finish;
    end
endmodule

Verilog/L10/public/vcd/tb_dff.vcd
$date
	Wed Oct 29 15:49:20 2025
$end
$version
	Icarus Verilog
$end
$timescale
	1s
$end
$scope module tb_dff $end
$scope module dut $end
$var wire 1 ! clk $end
$var wire 1 " d $end
$var wire 1 # reset $end
$var reg 1 $ q $end
$upscope $end
$upscope $end
$enddefinitions $end
#0
$dumpvars
x$
1#
0"
0!
$end
#5
0$
1!
#10
0!
0#
#15
1!
#20
0!
1"
#25
1$
1!
#30
0!
0"
#35
0$
1!
#40
0!
1"
#45
1$
1!
#50
0!
#55
1!
#60
0!
0"
#65
0$
1!
#70
0!
1#
#75
1!
#80
0!
0#
#85
1!
#90
0!
1"
#95
1$
1!
#100
0!
0"
#105
0$
1!
