Verilog/L3/src/chaos.v
module chaos (input X4, input X3, input X2, input X1, input X0, output F);
wire NX4, NX3, NX2, NX1, NX0;
wire w1, w2, w3, w4, w5;
not n1(NX4, X4);
not n2(NX3, X3);
not n3(NX2, X2);
not n4(NX1, X1);
not n5(NX0, X0);
and a1(w1, NX4, NX3, NX1);
and a2(w2, NX4, NX2, NX0);
and a3(w3, NX4, NX2, NX1);
and a4(w4, NX3, NX1, NX0);
and a5(w5, NX3, NX2, NX0);
or o1(F, w1, w2, w3, w4, w5);
endmodule

Verilog/L3/tb/tbChaos.v
`timescale 1ns/1ps
`include "src/chaos.v"

module tb;
    reg X4, X3, X2, X1, X0;
    wire F;

    chaos c1(.X4(X4), .X3(X3), .X2(X2), .X1(X1), .X0(X0), .F(F));

    initial begin
        $dumpfile("./public/vcd/waveChaos.vcd");
        $dumpvars(0, tb);

        $monitor("%0d X=%b%b%b%b%b F=%b", $time, X4, X3, X2, X1, X0, F);
        X4=0; X3=0; X2=0; X1=0; X0=0;
        repeat(32) begin
            #5 {X4,X3,X2,X1,X0} = {X4,X3,X2,X1,X0} + 1;
        end
        #5 $finish;
    end
endmodule

Verilog/L3/public/vcd/waveChaos.vcd
$date
	Wed Sep  3 15:35:03 2025
$end
$version
	Icarus Verilog
$end
$timescale
	1ps
$end
$scope module tb $end
$var wire 1 ! F $end
$var reg 1 " X0 $end
$var reg 1 # X1 $end
$var reg 1 $ X2 $end
$var reg 1 % X3 $end
$var reg 1 & X4 $end
$scope module c1 $end
$var wire 1 ! F $end
$var wire 1 ' NX0 $end
$var wire 1 ( NX1 $end
$var wire 1 ) NX2 $end
$var wire 1 * NX3 $end
$var wire 1 + NX4 $end
$var wire 1 " X0 $end
$var wire 1 # X1 $end
$var wire 1 $ X2 $end
$var wire 1 % X3 $end
$var wire 1 & X4 $end
$var wire 1 , w1 $end
$var wire 1 - w2 $end
$var wire 1 . w3 $end
$var wire 1 / w4 $end
$var wire 1 0 w5 $end
$upscope $end
$upscope $end
$enddefinitions $end
#0
$dumpvars
10
1/
1.
1-
1,
1+
1*
1)
1(
1'
0&
0%
0$
0#
0"
1!
$end
#5000
0-
0/
00
0'
1"
#10000
0,
0.
1-
10
0(
1'
1#
0"
#15000
0!
0-
00
0'
1"
#20000
1!
1,
1/
0)
1(
1'
1$
0#
0"
#25000
0/
0'
1"
#30000
0!
0,
0(
1'
1#
0"
#35000
0'
1"
#40000
1!
1.
1-
0*
1)
1(
1'
1%
0$
0#
0"
#45000
0-
0'
1"
#50000
0.
1-
0(
1'
1#
0"
#55000
0!
0-
0'
1"
#60000
0)
1(
1'
1$
0#
0"
#65000
0'
1"
#70000
0(
1'
1#
0"
#75000
0'
1"
#80000
1!
1/
10
0+
1*
1)
1(
1'
1&
0%
0$
0#
0"
#85000
0!
0/
00
0'
1"
#90000
1!
10
0(
1'
1#
0"
#95000
0!
00
0'
1"
#100000
1!
1/
0)
1(
1'
1$
0#
0"
#105000
0!
0/
0'
1"
#110000
0(
1'
1#
0"
#115000
0'
1"
#120000
0*
1)
1(
1'
1%
0$
0#
0"
#125000
0'
1"
#130000
0(
1'
1#
0"
#135000
0'
1"
#140000
0)
1(
1'
1$
0#
0"
#145000
0'
1"
#150000
0(
1'
1#
0"
#155000
0'
1"
#160000
1!
1,
1.
1-
1/
10
1+
1*
1)
1(
1'
0&
0%
0$
0#
0"
