Verilog/P8/Q1/gated_dff.v
module gated_dff (
    input  wire clk,
    input  wire rst_n,
    input  wire load,
    input  wire scrub,
    input  wire d,
    output reg  q
);
always @(posedge clk or negedge rst_n) begin
    if (!rst_n) begin
        q <= 0;
    end
    else if (scrub) begin
        q <= 0; //misprint in Q, if scrub is high, it resets Q to 0. this is basically active high synchronous reset
    end
    else if (load) begin
        q <= d;
    end
end
endmodule

//this flip flop essentially has two types of signals. 
//rst_n is active low asynchronous reset, highest priority
//scrub is active high synchronous reset
//load is to decide whether in memory state or sample input d. If load = 0, retain q.

Verilog/P8/Q3/state_register3.v
`include "../Q1/gated_dff.v"
module state_register3 (
    input  wire       clk,
    input  wire       rst_n,
    input  wire       load,
    input  wire [2:0] hold_mask,
    input  wire       scrub,
    input  wire [2:0] next_state,
    output wire [2:0] curr_state
);
    gated_dff gdf0(clk, rst_n, (load & (~hold_mask[0])), scrub, next_state[0], curr_state[0]); //either holds the current state or loads the next state
    gated_dff gdf1(clk, rst_n, (load & (~hold_mask[1])), scrub, next_state[1], curr_state[1]);
    gated_dff gdf2(clk, rst_n, (load & (~hold_mask[2])), scrub, next_state[2], curr_state[2]);
endmodule

//allows bits of our choice to be frozen while others can be updated, in a given clock cycle

Verilog/P8/Q3/tb_state_register3.v
`timescale 1ns/1ps
`include "state_register3.v"

module tb_state_register3;
    reg clk;
    reg rst_n;
    reg load;
    reg [2:0] hold_mask;
    reg scrub;
    reg [2:0] next_state;
    wire [2:0] curr_state;
    reg [2:0] expected;

    state_register3 uut (
        .clk(clk),
        .rst_n(rst_n),
        .load(load),
        .hold_mask(hold_mask),
        .scrub(scrub),
        .next_state(next_state),
        .curr_state(curr_state)
    );

    initial begin
        clk = 0;
        forever #5 clk = ~clk;
    end

    task check_state;
        begin
            @(posedge clk);
            #1;
            if (curr_state !== expected) begin
                $fatal(1, "State mismatch: expected %0b got %0b", expected, curr_state);
            end
        end
    endtask

    integer value;
    initial begin
        $dumpfile("tb_state_register3.vcd");
        $dumpvars(0, tb_state_register3);

        load = 0;
        hold_mask = 3'b000;
        scrub = 0;
        next_state = 3'b000;
        rst_n = 0;
        expected = 3'b000;
        #2;
        check_state();

        rst_n = 1;
        // Sweep through all possible next_state values with load asserted
        for (value = 0; value < 8; value = value + 1) begin
            next_state = value[2:0];
            load = 1;
            hold_mask = 3'b000;
            scrub = 0;
            expected = next_state;
            check_state();
        end

        // Apply selective hold on bit 1 while updating others
        load = 1;
        hold_mask = 3'b010;
        next_state = 3'b000;
        expected = {next_state[2], expected[1], next_state[0]};
        check_state();

        // Release hold and update all bits again
        hold_mask = 3'b000;
        next_state = 3'b101;
        expected = next_state;
        check_state();

        // Keep state frozen via hold mask even though load toggles
        hold_mask = 3'b111;
        load = 1;
        next_state = 3'b010;
        expected = expected; // unchanged
        check_state();

        // Scrub should clear regardless of hold mask or load
        hold_mask = 3'b111;
        load = 0;
        scrub = 1;
        expected = 3'b000;
        check_state();
        scrub = 0;

        // Drive to a non-zero state then pulse async reset mid-cycle
        hold_mask = 3'b000;
        load = 1;
        next_state = 3'b101;
        expected = next_state;
        check_state();
        #1;
        rst_n = 0;
        expected = 3'b000;
        #1;
        if (curr_state !== expected) $fatal(1, "Async reset failed to clear state");
        load = 1'b0;
        hold_mask = 3'b000;
        scrub = 1'b0;
        next_state = 3'b000;
        rst_n = 1;
        @(posedge clk);
        #1;
        if (curr_state !== expected) $fatal(1, "State should remain reset after releasing rst");

        $display("state_register3: all cases covered");
        $finish;
    end
endmodule

Verilog/P8/Q3/tb_state_register3.vcd
$date
	Mon Sep 29 16:32:23 2025
$end
$version
	Icarus Verilog
$end
$timescale
	1ps
$end
$scope module tb_state_register3 $end
$var wire 3 ! curr_state [2:0] $end
$var reg 1 " clk $end
$var reg 3 # expected [2:0] $end
$var reg 3 $ hold_mask [2:0] $end
$var reg 1 % load $end
$var reg 3 & next_state [2:0] $end
$var reg 1 ' rst_n $end
$var reg 1 ( scrub $end
$var integer 32 ) value [31:0] $end
$scope module uut $end
$var wire 1 " clk $end
$var wire 3 * hold_mask [2:0] $end
$var wire 1 % load $end
$var wire 3 + next_state [2:0] $end
$var wire 1 ' rst_n $end
$var wire 1 ( scrub $end
$var wire 3 , curr_state [2:0] $end
$scope module gdf0 $end
$var wire 1 " clk $end
$var wire 1 - d $end
$var wire 1 . load $end
$var wire 1 ' rst_n $end
$var wire 1 ( scrub $end
$var reg 1 / q $end
$upscope $end
$scope module gdf1 $end
$var wire 1 " clk $end
$var wire 1 0 d $end
$var wire 1 1 load $end
$var wire 1 ' rst_n $end
$var wire 1 ( scrub $end
$var reg 1 2 q $end
$upscope $end
$scope module gdf2 $end
$var wire 1 " clk $end
$var wire 1 3 d $end
$var wire 1 4 load $end
$var wire 1 ' rst_n $end
$var wire 1 ( scrub $end
$var reg 1 5 q $end
$upscope $end
$upscope $end
$scope task check_state $end
$upscope $end
$upscope $end
$enddefinitions $end
$comment Show the parameter values. $end
$dumpall
$end
#0
$dumpvars
05
04
03
02
01
00
0/
0.
0-
b0 ,
b0 +
b0 *
bx )
0(
0'
b0 &
0%
b0 $
b0 #
0"
b0 !
$end
#5000
1"
#6000
1.
11
14
1%
b0 )
1'
#10000
0"
#15000
1"
#16000
1-
b1 #
b1 &
b1 +
b1 )
#20000
0"
#25000
b1 !
b1 ,
1/
1"
#26000
0-
10
b10 #
b10 &
b10 +
b10 )
#30000
0"
#35000
0/
b10 !
b10 ,
12
1"
#36000
1-
b11 #
b11 &
b11 +
b11 )
#40000
0"
#45000
b11 !
b11 ,
1/
1"
#46000
0-
00
13
b100 #
b100 &
b100 +
b100 )
#50000
0"
#55000
0/
02
b100 !
b100 ,
15
1"
#56000
1-
b101 #
b101 &
b101 +
b101 )
#60000
0"
#65000
b101 !
b101 ,
1/
1"
#66000
0-
10
b110 #
b110 &
b110 +
b110 )
#70000
0"
#75000
0/
b110 !
b110 ,
12
1"
#76000
1-
b111 #
b111 &
b111 +
b111 )
#80000
0"
#85000
b111 !
b111 ,
1/
1"
#86000
01
0-
00
03
b10 #
b0 &
b0 +
b10 $
b10 *
b1000 )
#90000
0"
#95000
0/
b10 !
b10 ,
05
1"
#96000
11
1-
13
b101 #
b101 &
b101 +
b0 $
b0 *
#100000
0"
#105000
15
02
b101 !
b101 ,
1/
1"
#106000
0.
01
04
0-
10
03
b10 &
b10 +
b111 $
b111 *
#110000
0"
#115000
1"
#116000
b0 #
1(
0%
#120000
0"
#125000
05
b0 !
b0 ,
0/
1"
#126000
1.
11
14
1-
00
13
b101 #
b101 &
b101 +
1%
b0 $
b0 *
0(
#130000
0"
#135000
1/
b101 !
b101 ,
15
1"
#137000
05
b0 !
b0 ,
0/
b0 #
0'
#138000
0-
03
0.
01
04
1'
b0 &
b0 +
0%
