Verilog/P10/both.v
//counter that does both up and down - mode decided by input
module jkfflop(input  J, K , clk ,rst, mode, output reg Q);
    always @(negedge clk or posedge rst) begin 
        if(rst) begin
            Q <= mode ? 1'b1 : 1'b0; //if mode is 1 (down counting) reset to 1 else reset to 0 //if using M-2 then simply do Q <= 1'b0;
        end
        else begin
            case({J,K})
                2'b01: Q <= 1'b0;
                2'b10: Q <= 1'b1;
                2'b11: Q <= ~Q;
            endcase
        end
    end
endmodule

module BCD_Counter(input clk, rst, mode, output [3:0] Q);

    wire [3:0] T;
    jkfflop j1(1'b1 ,1'b1, clk, rst, mode, T[0]);
    jkfflop j2(1'b1, 1'b1, (mode ? ~T[0] : T[0]), rst, mode, T[1]); //if mode is 1 then down counter
    jkfflop j3(1'b1, 1'b1, (mode ? ~T[1] : T[1]), rst, mode, T[2]);
    jkfflop j4(1'b1, 1'b1, (mode ? ~T[2] : T[2]), rst, mode, T[3]);
    assign Q = {T[3], T[2], T[1], T[0]};

/* //M2
    wire [3:0] T;
    jkfflop j1(1'b1 ,1'b1, clk, rst, mode, T[0]);
    jkfflop j2(1'b1, 1'b1, T[0], rst, mode, T[1]); //if mode is 1 then down counter
    jkfflop j3(1'b1, 1'b1, T[1], rst, mode, T[2]);
    jkfflop j4(1'b1, 1'b1, T[2], rst, mode, T[3]);
    assign Q = (!mode) ? {T[3], T[2], T[1], T[0]} : {~T[3], ~T[2], ~T[1], ~T[0]};
*/
endmodule

//small issue in both implementation, look at output
//to avoid this gemini says use synchronous

Verilog/P10/tb_both.v
// Testbench for BCD_Counter (both.v)
// Generates clock, toggles mode for up/down counting, applies reset,
// prints the counter value and creates a VCD file for waveform inspection.
`include "both.v"
`timescale 1ns/1ps

module tb_both();
    reg clk;
    reg rst;
    reg mode; // 0 => up, 1 => down
    wire [3:0] Q;

    // Instantiate DUT
    BCD_Counter dut(.clk(clk), .rst(rst), .mode(mode), .Q(Q));

    // Clock: 10 ns period (100 MHz), toggle every 5 ns
    initial begin
        clk = 0;
        forever #5 clk = ~clk;
    end

    // Test sequence
    initial begin
        // VCD dump for waveform viewers
        $dumpfile("tb_both.vcd");
        $dumpvars(0, tb_both);

        // initialize
        rst = 1'b1;
        mode = 1'b0; // start with up-count
        #17; // wait some time (non-multiple of clock edge to show asynchronous behavior)
        rst = 1'b0; // release reset

        $display("%0t ns: Released reset, starting up-count", $time);

        // Let it count up for several cycles
        #200;

        // Switch to down-counting
        mode = 1'b1;
        $display("%0t ns: Switching to down-count", $time);
        #200;

        // Pulse external reset to observe behavior
        $display("%0t ns: Asserting external reset", $time);
        rst = 1'b1;
        #25;
        rst = 1'b0;
        $display("%0t ns: Released external reset", $time);
        #100;

        $display("%0t ns: Test complete, finishing simulation", $time);
        $finish;
    end

    // Monitor the signals at each clock edge
    always @(negedge clk) begin
        $display("%0t ns | clk=%b rst=%b mode=%b | Q=%b (%0d)", $time, clk, rst, mode, Q, Q);
    end

endmodule

Verilog/P10/tb_both.vcd
$date
	Wed Oct 29 13:45:58 2025
$end
$version
	Icarus Verilog
$end
$timescale
	1ps
$end
$scope module tb_both $end
$var wire 4 ! Q [3:0] $end
$var reg 1 " clk $end
$var reg 1 # mode $end
$var reg 1 $ rst $end
$scope module dut $end
$var wire 1 " clk $end
$var wire 1 # mode $end
$var wire 1 $ rst $end
$var wire 4 % T [3:0] $end
$var wire 4 & Q [3:0] $end
$scope module j1 $end
$var wire 1 ' J $end
$var wire 1 ( K $end
$var wire 1 " clk $end
$var wire 1 # mode $end
$var wire 1 $ rst $end
$var reg 1 ) Q $end
$upscope $end
$scope module j2 $end
$var wire 1 * J $end
$var wire 1 + K $end
$var wire 1 , clk $end
$var wire 1 # mode $end
$var wire 1 $ rst $end
$var reg 1 - Q $end
$upscope $end
$scope module j3 $end
$var wire 1 . J $end
$var wire 1 / K $end
$var wire 1 0 clk $end
$var wire 1 # mode $end
$var wire 1 $ rst $end
$var reg 1 1 Q $end
$upscope $end
$scope module j4 $end
$var wire 1 2 J $end
$var wire 1 3 K $end
$var wire 1 4 clk $end
$var wire 1 # mode $end
$var wire 1 $ rst $end
$var reg 1 5 Q $end
$upscope $end
$upscope $end
$upscope $end
$enddefinitions $end
$comment Show the parameter values. $end
$dumpall
$end
#0
$dumpvars
05
04
13
12
01
00
1/
1.
0-
0,
1+
1*
0)
1(
1'
b0 &
b0 %
1$
0#
0"
b0 !
$end
#5000
1"
#10000
0"
#15000
1"
#17000
0$
#20000
1,
b1 !
b1 &
b1 %
1)
0"
#25000
1"
#30000
10
1-
0,
b10 !
b10 &
b10 %
0)
0"
#35000
1"
#40000
1,
b11 !
b11 &
b11 %
1)
0"
#45000
1"
#50000
14
11
00
0-
0,
b100 !
b100 &
b100 %
0)
0"
#55000
1"
#60000
1,
b101 !
b101 &
b101 %
1)
0"
#65000
1"
#70000
10
1-
0,
b110 !
b110 &
b110 %
0)
0"
#75000
1"
#80000
1,
b111 !
b111 &
b111 %
1)
0"
#85000
1"
#90000
15
04
01
00
0-
0,
b1000 !
b1000 &
b1000 %
0)
0"
#95000
1"
#100000
1,
b1001 !
b1001 &
b1001 %
1)
0"
#105000
1"
#110000
10
1-
0,
b1010 !
b1010 &
b1010 %
0)
0"
#115000
1"
#120000
1,
b1011 !
b1011 &
b1011 %
1)
0"
#125000
1"
#130000
14
11
00
0-
0,
b1100 !
b1100 &
b1100 %
0)
0"
#135000
1"
#140000
1,
b1101 !
b1101 &
b1101 %
1)
0"
#145000
1"
#150000
10
1-
0,
b1110 !
b1110 &
b1110 %
0)
0"
#155000
1"
#160000
1,
b1111 !
b1111 &
b1111 %
1)
0"
#165000
1"
#170000
05
04
01
00
0-
0,
b0 !
b0 &
b0 %
0)
0"
#175000
1"
#180000
1,
b1 !
b1 &
b1 %
1)
0"
#185000
1"
#190000
10
1-
0,
b10 !
b10 &
b10 %
0)
0"
#195000
1"
#200000
1,
b11 !
b11 &
b11 %
1)
0"
#205000
1"
#210000
14
11
00
0-
0,
b100 !
b100 &
b100 %
0)
0"
#215000
1"
#217000
b1100 !
b1100 &
b1100 %
15
1,
10
04
1#
#220000
14
01
00
1-
0,
b1011 !
b1011 &
b1011 %
1)
0"
#225000
1"
#230000
1,
b1010 !
b1010 &
b1010 %
0)
0"
#235000
1"
#240000
10
0-
0,
b1001 !
b1001 &
b1001 %
1)
0"
#245000
1"
#250000
1,
b1000 !
b1000 &
b1000 %
0)
0"
#255000
1"
#260000
05
04
11
00
1-
0,
b111 !
b111 &
b111 %
1)
0"
#265000
1"
#270000
1,
b110 !
b110 &
b110 %
0)
0"
#275000
1"
#280000
10
0-
0,
b101 !
b101 &
b101 %
1)
0"
#285000
1"
#290000
1,
b100 !
b100 &
b100 %
0)
0"
#295000
1"
#300000
14
01
00
1-
0,
b11 !
b11 &
b11 %
1)
0"
#305000
1"
#310000
1,
b10 !
b10 &
b10 %
0)
0"
#315000
1"
#320000
10
0-
0,
b1 !
b1 &
b1 %
1)
0"
#325000
1"
#330000
1,
b0 !
b0 &
b0 %
0)
0"
#335000
1"
#340000
15
04
11
00
1-
0,
b1111 !
b1111 &
b1111 %
1)
0"
#345000
1"
#350000
1,
b1110 !
b1110 &
b1110 %
0)
0"
#355000
1"
#360000
10
0-
0,
b1101 !
b1101 &
b1101 %
1)
0"
#365000
1"
#370000
1,
b1100 !
b1100 &
b1100 %
0)
0"
#375000
1"
#380000
14
01
00
1-
0,
b1011 !
b1011 &
b1011 %
1)
0"
#385000
1"
#390000
1,
b1010 !
b1010 &
b1010 %
0)
0"
#395000
1"
#400000
10
0-
0,
b1001 !
b1001 &
b1001 %
1)
0"
#405000
1"
#410000
1,
b1000 !
b1000 &
b1000 %
0)
0"
#415000
1"
#417000
0,
00
04
b1111 !
b1111 &
1)
1-
b1111 %
11
1$
#420000
0"
#425000
1"
#430000
0"
#435000
1"
#440000
0"
#442000
0$
#445000
1"
#450000
1,
b1110 !
b1110 &
b1110 %
0)
0"
#455000
1"
#460000
10
0-
0,
b1101 !
b1101 &
b1101 %
1)
0"
#465000
1"
#470000
1,
b1100 !
b1100 &
b1100 %
0)
0"
#475000
1"
#480000
14
01
00
1-
0,
b1011 !
b1011 &
b1011 %
1)
0"
#485000
1"
#490000
1,
b1010 !
b1010 &
b1010 %
0)
0"
#495000
1"
#500000
10
0-
0,
b1001 !
b1001 &
b1001 %
1)
0"
#505000
1"
#510000
1,
b1000 !
b1000 &
b1000 %
0)
0"
#515000
1"
#520000
05
04
11
00
1-
0,
b111 !
b111 &
b111 %
1)
0"
#525000
1"
#530000
1,
b110 !
b110 &
b110 %
0)
0"
#535000
1"
#540000
10
0-
0,
b101 !
b101 &
b101 %
1)
0"
