Verilog/L5/src/priority_encoder_4to2.v
module priority_encoder_4to2(
    output [1:0] Y,
    output V,
    input [3:0] I,
    input E
);
    buf B1(Y[1], (I[3]|I[2])&E);
    buf B2(Y[0], ((I[3]|(~I[2])&I[1])&E));
    buf B3(V, E&(I[3]|I[2]|I[1]|I[0]));
endmodule

Verilog/L5/tb/tb_priority_encoder_4to2.v
`timescale 1ns/1ps
`include "src/priority_encoder_4to2.v"

module tb_priority_encoder_4to2;

    reg [3:0] I;
    reg E;
    wire [1:0] Y;
    wire V;

    priority_encoder_4to2 uut(
        .Y(Y),
        .V(V),
        .I(I),
        .E(E)
    );

    initial begin
        $dumpfile("public/vcd/wave_priority_encoder_4to2.vcd");
        $dumpvars(0, tb_priority_encoder_4to2);

        $display("\nTesting 4:2 Priority Encoder\n");
        $display("|%-5s|%-5s|%-5s|%-5s|%-5s|", "Time", "I", "E", "Y", "V");
        $display("|-----|-----|-----|-----|-----|");

        $monitor("|%-5d|%-5b|%-5b|%-5b|%-5b|", 
                 $time, I, E, Y, V);

        // Apply all input cases
            I = 4'b0001; E = 1'b0;
        #10 I = 4'b0010; E = 1'b0;
        #10 I = 4'b0000; E = 1'b1;
        #10 I = 4'b0001; E = 1'b1;
        #10 I = 4'b0010; E = 1'b1;
        #10 I = 4'b0011; E = 1'b1;
        #10 I = 4'b0100; E = 1'b1;
        #10 I = 4'b0101; E = 1'b1;
        #10 I = 4'b0110; E = 1'b0;
        #10 I = 4'b0110; E = 1'b1;
        #10 I = 4'b0111; E = 1'b1;
        #10 I = 4'b1000; E = 1'b1;
        #10 I = 4'b1001; E = 1'b1;
        #10 I = 4'b1010; E = 1'b1;
        #10 I = 4'b1011; E = 1'b1;
        #10 I = 4'b1100; E = 1'b1;
        #10 I = 4'b1101; E = 1'b1;
        #10 I = 4'b1110; E = 1'b1;
        #10 I = 4'b1111; E = 1'b1;

        #10 $finish;
    end
endmodule

Verilog/L5/public/vcd/wave_priority_encoder_4to2.vcd
$date
	Wed Sep 17 15:39:31 2025
$end
$version
	Icarus Verilog
$end
$timescale
	1ps
$end
$scope module tb_priority_encoder_4to2 $end
$var wire 2 ! Y [1:0] $end
$var wire 1 " V $end
$var reg 1 # E $end
$var reg 4 $ I [3:0] $end
$scope module uut $end
$var wire 1 # E $end
$var wire 4 % I [3:0] $end
$var wire 1 " V $end
$var wire 2 & Y [1:0] $end
$upscope $end
$upscope $end
$enddefinitions $end
#0
$dumpvars
b0 &
b1 %
b1 $
0#
0"
b0 !
$end
#10000
b10 $
b10 %
#20000
b0 !
b0 &
0"
1#
b0 $
b0 %
#30000
1"
b1 $
b1 %
#40000
b1 !
b1 &
1"
b10 $
b10 %
#50000
b11 $
b11 %
#60000
1"
b10 !
b10 &
b100 $
b100 %
#70000
b101 $
b101 %
#80000
b0 !
b0 &
0"
0#
b110 $
b110 %
#90000
b10 !
b10 &
1"
1#
#100000
b111 $
b111 %
#110000
b11 !
b11 &
b1000 $
b1000 %
#120000
b1001 $
b1001 %
#130000
b1010 $
b1010 %
#140000
b1011 $
b1011 %
#150000
b1100 $
b1100 %
#160000
b1101 $
b1101 %
#170000
b1110 $
b1110 %
#180000
b1111 $
b1111 %
