Verilog/P6/Q4/encoder_32to5.v
// 32-to-5 Encoder (Behavioral)
module encoder32to5 (
    input  wire [31:0] in,   // 32-bit one-hot input
    output reg  [4:0] out    // Encoded 5-bit output
);
    /*
    always @(*) begin
        out=5'b0;
        case(1'b1)
        in[0]: out=0;
        in[1]: out=1;
        in[2]: out=2;
        in[3]: out=3;
        in[4]: out=4;
        in[5]: out=5;
        in[6]: out=6;
        in[7]: out=7;
        in[8]: out=8;
        in[9]: out=9;
        in[10]: out=10;
        in[11]: out=11;
        in[12]: out=12;
        in[13]: out=13;
        in[14]: out=14;
        in[15]: out=15;
        in[16]: out=16;
        in[17]: out=17;
        in[18]: out=18;
        in[19]: out=19;
        in[20]: out=20;
        in[21]: out=21;
        in[22]: out=22;
        in[23]: out=23;
        in[24]: out=24;
        in[25]: out=25;
        in[26]: out=26;
        in[27]: out=27;
        in[28]: out=28;
        in[29]: out=29;
        in[30]: out=30;
        in[31]: out=31;
        endcase
        */
    integer i;
    always @(*) begin
        out = 5'b0;
        for(i=0;i<32;i=i+1) begin
            if(in[i]) begin
                out = i; //automatically type casts
            end
        end
    end
    
endmodule

Verilog/P6/Q4/tb_encoder_32to5.v
`include "encoder_32to5.v"
module tb_encoder32to5;

    reg [31:0] in;
    wire [4:0] out;

    // Instantiate the encoder
    encoder32to5 uut (
        .in(in),
        .out(out)
    );

    integer i;

    initial begin
        $dumpfile("encoder32to5_tb.vcd"); // for GTKWave
        $dumpvars(0, tb_encoder32to5);

        $display("Input Position | Encoded Output");
        $display("-------------------------------");

        // Apply one-hot inputs
        for (i = 0; i < 32; i = i + 1) begin
            in = 32'b1 << i;  // one-hot at position i
            #5;
            $display("     %2d        |     %2d", i, out);
        end

        $finish;
    end

endmodule

Verilog/P6/Q4/encoder32to5_tb.vcd
$date
	Sun Sep 21 17:24:08 2025
$end
$version
	Icarus Verilog
$end
$timescale
	1s
$end
$scope module tb_encoder32to5 $end
$var wire 5 ! out [4:0] $end
$var reg 32 " in [31:0] $end
$var integer 32 # i [31:0] $end
$scope module uut $end
$var wire 32 $ in [31:0] $end
$var reg 5 % out [4:0] $end
$var integer 32 & i [31:0] $end
$upscope $end
$upscope $end
$enddefinitions $end
$comment Show the parameter values. $end
$dumpall
$end
#0
$dumpvars
b100000 &
b0 %
b1 $
b0 #
b1 "
b0 !
$end
#5
b1 !
b1 %
b100000 &
b10 "
b10 $
b1 #
#10
b100000 &
b10 !
b10 %
b100 "
b100 $
b10 #
#15
b100000 &
b11 !
b11 %
b1000 "
b1000 $
b11 #
#20
b100000 &
b100 !
b100 %
b10000 "
b10000 $
b100 #
#25
b100000 &
b101 !
b101 %
b100000 "
b100000 $
b101 #
#30
b100000 &
b110 !
b110 %
b1000000 "
b1000000 $
b110 #
#35
b100000 &
b111 !
b111 %
b10000000 "
b10000000 $
b111 #
#40
b100000 &
b1000 !
b1000 %
b100000000 "
b100000000 $
b1000 #
#45
b100000 &
b1001 !
b1001 %
b1000000000 "
b1000000000 $
b1001 #
#50
b100000 &
b1010 !
b1010 %
b10000000000 "
b10000000000 $
b1010 #
#55
b100000 &
b1011 !
b1011 %
b100000000000 "
b100000000000 $
b1011 #
#60
b100000 &
b1100 !
b1100 %
b1000000000000 "
b1000000000000 $
b1100 #
#65
b100000 &
b1101 !
b1101 %
b10000000000000 "
b10000000000000 $
b1101 #
#70
b100000 &
b1110 !
b1110 %
b100000000000000 "
b100000000000000 $
b1110 #
#75
b100000 &
b1111 !
b1111 %
b1000000000000000 "
b1000000000000000 $
b1111 #
#80
b100000 &
b10000 !
b10000 %
b10000000000000000 "
b10000000000000000 $
b10000 #
#85
b100000 &
b10001 !
b10001 %
b100000000000000000 "
b100000000000000000 $
b10001 #
#90
b100000 &
b10010 !
b10010 %
b1000000000000000000 "
b1000000000000000000 $
b10010 #
#95
b100000 &
b10011 !
b10011 %
b10000000000000000000 "
b10000000000000000000 $
b10011 #
#100
b100000 &
b10100 !
b10100 %
b100000000000000000000 "
b100000000000000000000 $
b10100 #
#105
b100000 &
b10101 !
b10101 %
b1000000000000000000000 "
b1000000000000000000000 $
b10101 #
#110
b100000 &
b10110 !
b10110 %
b10000000000000000000000 "
b10000000000000000000000 $
b10110 #
#115
b100000 &
b10111 !
b10111 %
b100000000000000000000000 "
b100000000000000000000000 $
b10111 #
#120
b100000 &
b11000 !
b11000 %
b1000000000000000000000000 "
b1000000000000000000000000 $
b11000 #
#125
b100000 &
b11001 !
b11001 %
b10000000000000000000000000 "
b10000000000000000000000000 $
b11001 #
#130
b100000 &
b11010 !
b11010 %
b100000000000000000000000000 "
b100000000000000000000000000 $
b11010 #
#135
b100000 &
b11011 !
b11011 %
b1000000000000000000000000000 "
b1000000000000000000000000000 $
b11011 #
#140
b100000 &
b11100 !
b11100 %
b10000000000000000000000000000 "
b10000000000000000000000000000 $
b11100 #
#145
b100000 &
b11101 !
b11101 %
b100000000000000000000000000000 "
b100000000000000000000000000000 $
b11101 #
#150
b100000 &
b11110 !
b11110 %
b1000000000000000000000000000000 "
b1000000000000000000000000000000 $
b11110 #
#155
b100000 &
b11111 !
b11111 %
b10000000000000000000000000000000 "
b10000000000000000000000000000000 $
b11111 #
#160
b100000 #
